[
  {
    "uuid": "d987a845-2f03-46d3-93ec-0f53e96f0230",
    "name": "Reinold",
    "isFavourite": true,
    "image": "http://dummyimage.com/110x246.jpg/ff4444/ffffff",
    "groups": []
  },
  {
    "uuid": "c4330c81-5dd2-40c1-a951-1a7d01c75839",
    "name": "Morrie",
    "isFavourite": false,
    "image": "http://dummyimage.com/250x114.png/cc0000/ffffff",
    "groups": []
  },
  {
    "uuid": "7b0440d3-592e-424b-a6f4-4ba22b5fee08",
    "name": "Sibelle",
    "isFavourite": true,
    "image": "http://dummyimage.com/141x226.png/5fa2dd/ffffff",
    "groups": []
  },
  {
    "uuid": "0c6acb5e-8130-4f46-abf5-d16eb17844a9",
    "name": "Waldemar",
    "isFavourite": true,
    "image": "http://dummyimage.com/113x147.bmp/ff4444/ffffff",
    "groups": []
  },
  {
    "uuid": "0f8a05bf-ec1a-46d9-9e49-0e3587b59e4a",
    "name": "Jojo",
    "isFavourite": false,
    "image": "http://dummyimage.com/221x125.jpg/cc0000/ffffff",
    "groups": []
  },
  {
    "uuid": "c6574aef-9e4c-4715-b8d0-04448dd46b06",
    "name": "Amber",
    "isFavourite": true,
    "image": "http://dummyimage.com/205x144.bmp/5fa2dd/ffffff",
    "groups": []
  },
  {
    "uuid": "fa65cb3b-a76f-43ea-8838-d882cb1273a0",
    "name": "Maure",
    "isFavourite": true,
    "image": "http://dummyimage.com/211x247.jpg/ff4444/ffffff",
    "groups": []
  },
  {
    "uuid": "91d05ba6-51ff-4329-95b3-d627c3fd3439",
    "name": "Estevan",
    "isFavourite": true,
    "image": "http://dummyimage.com/208x238.png/dddddd/000000",
    "groups": []
  },
  {
    "uuid": "c9e84103-3420-49cf-81f3-239aaed21bdb",
    "name": "Ardis",
    "isFavourite": false,
    "image": "http://dummyimage.com/244x234.bmp/cc0000/ffffff",
    "groups": []
  },
  {
    "uuid": "f1bb20de-b695-4c32-b170-042fd43aeb91",
    "name": "Maiga",
    "isFavourite": false,
    "image": "http://dummyimage.com/184x171.bmp/5fa2dd/ffffff",
    "groups": []
  },
  {
    "uuid": "8a946242-381b-43ea-b10d-11b586908f97",
    "name": "Caitlin",
    "isFavourite": false,
    "image": "http://dummyimage.com/103x245.jpg/cc0000/ffffff",
    "groups": []
  },
  {
    "uuid": "6d8e7770-1377-4481-b806-9d47ae3e728b",
    "name": "Concordia",
    "isFavourite": false,
    "image": "http://dummyimage.com/156x129.bmp/cc0000/ffffff",
    "groups": []
  },
  {
    "uuid": "c18516dd-cb6e-4dd4-977a-dcf833097a3e",
    "name": "Ulric",
    "isFavourite": true,
    "image": "http://dummyimage.com/164x223.jpg/ff4444/ffffff",
    "groups": []
  },
  {
    "uuid": "c3e0f49b-127a-4569-88c4-3a77f860ec6c",
    "name": "Laurianne",
    "isFavourite": false,
    "image": "http://dummyimage.com/235x241.png/cc0000/ffffff",
    "groups": []
  },
  {
    "uuid": "733ca7e8-3e02-4b3d-9d94-834afc259096",
    "name": "Mead",
    "isFavourite": true,
    "image": "http://dummyimage.com/236x152.bmp/ff4444/ffffff",
    "groups": []
  },
  {
    "uuid": "88c2beb1-5b32-45ec-a644-f97613cb1aa9",
    "name": "Barbabas",
    "isFavourite": true,
    "image": "http://dummyimage.com/135x133.bmp/5fa2dd/ffffff",
    "groups": []
  },
  {
    "uuid": "baf31f5f-b1e9-48af-a103-fb43915415cb",
    "name": "Kenna",
    "isFavourite": true,
    "image": "http://dummyimage.com/239x197.jpg/dddddd/000000",
    "groups": []
  },
  {
    "uuid": "b0bb69e8-0dc0-4104-852b-7e53889d2351",
    "name": "Pia",
    "isFavourite": true,
    "image": "http://dummyimage.com/135x214.png/ff4444/ffffff",
    "groups": []
  },
  {
    "uuid": "6f79a34c-6f01-4c19-b6cb-bb17d1a046af",
    "name": "Devonna",
    "isFavourite": true,
    "image": "http://dummyimage.com/146x240.jpg/cc0000/ffffff",
    "groups": []
  },
  {
    "uuid": "54903da6-b8bf-47a6-a98e-57ecad246322",
    "name": "Erin",
    "isFavourite": true,
    "image": "http://dummyimage.com/113x152.bmp/ff4444/ffffff",
    "groups": []
  },
  {
    "uuid": "675793a2-f8cb-4414-867a-0e00c9ece4b9",
    "name": "Denys",
    "isFavourite": true,
    "image": "http://dummyimage.com/160x236.bmp/5fa2dd/ffffff",
    "groups": []
  },
  {
    "uuid": "121ffbcf-6607-4183-a7d9-9ea929922149",
    "name": "Lishe",
    "isFavourite": true,
    "image": "http://dummyimage.com/140x167.bmp/dddddd/000000",
    "groups": []
  },
  {
    "uuid": "44ec943a-54cb-4dcb-8aaa-b8abd97fbe40",
    "name": "Osborn",
    "isFavourite": true,
    "image": "http://dummyimage.com/136x116.jpg/cc0000/ffffff",
    "groups": []
  },
  {
    "uuid": "b657449d-478f-4f48-8ef3-c86459c636d3",
    "name": "Deloria",
    "isFavourite": true,
    "image": "http://dummyimage.com/211x140.png/cc0000/ffffff",
    "groups": []
  },
  {
    "uuid": "53cb6e09-3721-442b-94c6-b8f7340209cd",
    "name": "Kinna",
    "isFavourite": true,
    "image": "http://dummyimage.com/111x244.jpg/cc0000/ffffff",
    "groups": []
  },
  {
    "uuid": "3cc49708-c992-461f-ad02-e223fe15077d",
    "name": "Siegfried",
    "isFavourite": false,
    "image": "http://dummyimage.com/205x207.png/5fa2dd/ffffff",
    "groups": []
  },
  {
    "uuid": "1a4a9895-e28a-41ad-b30e-9976f69d6c32",
    "name": "Pepi",
    "isFavourite": true,
    "image": "http://dummyimage.com/125x199.bmp/5fa2dd/ffffff",
    "groups": []
  },
  {
    "uuid": "c8bfecbf-8293-42ab-b1dd-954fd2fe0efb",
    "name": "Gerhardine",
    "isFavourite": false,
    "image": "http://dummyimage.com/163x220.jpg/ff4444/ffffff",
    "groups": []
  },
  {
    "uuid": "0781a510-c66a-4996-a33e-560eb24593af",
    "name": "Kippy",
    "isFavourite": false,
    "image": "http://dummyimage.com/185x107.png/ff4444/ffffff",
    "groups": []
  },
  {
    "uuid": "399b378a-2624-443a-9dc7-9e7fce199258",
    "name": "Tonnie",
    "isFavourite": false,
    "image": "http://dummyimage.com/179x220.png/dddddd/000000",
    "groups": []
  },
  {
    "uuid": "6840c817-0b97-4618-8f5f-18f6c648ab0d",
    "name": "Gilli",
    "isFavourite": false,
    "image": "http://dummyimage.com/235x201.bmp/dddddd/000000",
    "groups": []
  },
  {
    "uuid": "6cea2406-8112-4214-af1c-5b388b329353",
    "name": "Katusha",
    "isFavourite": true,
    "image": "http://dummyimage.com/107x155.jpg/ff4444/ffffff",
    "groups": []
  },
  {
    "uuid": "ca7d73c3-0e3f-41d1-b3b4-92dd835c4f4c",
    "name": "Obadias",
    "isFavourite": false,
    "image": "http://dummyimage.com/197x121.bmp/dddddd/000000",
    "groups": []
  },
  {
    "uuid": "85dc5121-2664-4afe-9556-d2a29382f609",
    "name": "Elise",
    "isFavourite": true,
    "image": "http://dummyimage.com/150x226.png/5fa2dd/ffffff",
    "groups": []
  },
  {
    "uuid": "c3b23e60-8ce7-4a48-9fd3-848ad5669c89",
    "name": "Lauretta",
    "isFavourite": true,
    "image": "http://dummyimage.com/175x100.jpg/cc0000/ffffff",
    "groups": []
  },
  {
    "uuid": "466a3c43-408d-46d2-81a6-6591c28a6c98",
    "name": "Concordia",
    "isFavourite": true,
    "image": "http://dummyimage.com/242x149.bmp/5fa2dd/ffffff",
    "groups": []
  },
  {
    "uuid": "80626658-a647-4a6b-b768-4114faf221ab",
    "name": "Starla",
    "isFavourite": false,
    "image": "http://dummyimage.com/142x120.bmp/dddddd/000000",
    "groups": []
  },
  {
    "uuid": "dd0b09d2-ff0b-4b62-a4bf-76012aa3baea",
    "name": "Rickie",
    "isFavourite": true,
    "image": "http://dummyimage.com/227x110.jpg/cc0000/ffffff",
    "groups": []
  },
  {
    "uuid": "8c603cdf-b3fe-41ba-8e38-eb6b6e59e016",
    "name": "Kaela",
    "isFavourite": false,
    "image": "http://dummyimage.com/241x166.png/5fa2dd/ffffff",
    "groups": []
  },
  {
    "uuid": "dcc81e36-17be-412a-85c9-22872afa01b4",
    "name": "Cordey",
    "isFavourite": true,
    "image": "http://dummyimage.com/168x149.bmp/ff4444/ffffff",
    "groups": []
  },
  {
    "uuid": "1442a514-b67e-447a-8210-2b40bd714e22",
    "name": "Keane",
    "isFavourite": true,
    "image": "http://dummyimage.com/180x100.jpg/ff4444/ffffff",
    "groups": []
  },
  {
    "uuid": "96e2e804-2de1-403b-800e-7f22ba294754",
    "name": "Miguela",
    "isFavourite": true,
    "image": "http://dummyimage.com/102x125.png/5fa2dd/ffffff",
    "groups": []
  },
  {
    "uuid": "4786c8db-4169-4604-ab29-25e3af9a50d0",
    "name": "Erny",
    "isFavourite": false,
    "image": "http://dummyimage.com/210x189.bmp/cc0000/ffffff",
    "groups": []
  },
  {
    "uuid": "1c9c9266-2994-42b0-9888-4730b66f8c4f",
    "name": "Enrique",
    "isFavourite": false,
    "image": "http://dummyimage.com/131x165.bmp/dddddd/000000",
    "groups": []
  },
  {
    "uuid": "edfad4ca-2c26-480c-a684-3b43a81a0763",
    "name": "Michaella",
    "isFavourite": true,
    "image": "http://dummyimage.com/172x206.jpg/5fa2dd/ffffff",
    "groups": []
  },
  {
    "uuid": "ecac5cfd-db47-45ad-b0d9-cc3f2d714069",
    "name": "Issiah",
    "isFavourite": false,
    "image": "http://dummyimage.com/106x235.bmp/5fa2dd/ffffff",
    "groups": []
  },
  {
    "uuid": "b5ca8ef6-e7d6-414f-9e1d-7a889f706e76",
    "name": "Kizzee",
    "isFavourite": true,
    "image": "http://dummyimage.com/147x138.jpg/cc0000/ffffff",
    "groups": []
  },
  {
    "uuid": "4c97bde2-9a45-4286-9c54-f98ab991e4aa",
    "name": "Mariejeanne",
    "isFavourite": false,
    "image": "http://dummyimage.com/197x111.bmp/dddddd/000000",
    "groups": []
  },
  {
    "uuid": "73991167-a989-41fe-95fb-c3ab4462f70d",
    "name": "Westley",
    "isFavourite": true,
    "image": "http://dummyimage.com/179x161.bmp/ff4444/ffffff",
    "groups": []
  },
  {
    "uuid": "73693feb-51f1-436a-b2e8-ee4f1c17d37b",
    "name": "Mignon",
    "isFavourite": true,
    "image": "http://dummyimage.com/166x221.bmp/cc0000/ffffff",
    "groups": []
  },
  {
    "uuid": "21fbb48c-4d86-4f4d-bf70-6d92c1279014",
    "name": "Berkie",
    "isFavourite": true,
    "image": "http://dummyimage.com/171x215.bmp/cc0000/ffffff",
    "groups": []
  },
  {
    "uuid": "87c06a27-8f3b-498c-b874-c004b0663a67",
    "name": "Burch",
    "isFavourite": true,
    "image": "http://dummyimage.com/107x134.bmp/cc0000/ffffff",
    "groups": []
  },
  {
    "uuid": "e210912c-8281-406d-8f35-fa6930d84c71",
    "name": "Paige",
    "isFavourite": false,
    "image": "http://dummyimage.com/154x249.bmp/dddddd/000000",
    "groups": []
  },
  {
    "uuid": "a33e284b-db7d-4fe7-a28b-9ff321b03c7e",
    "name": "Darcy",
    "isFavourite": false,
    "image": "http://dummyimage.com/102x196.png/5fa2dd/ffffff",
    "groups": []
  },
  {
    "uuid": "67dcac83-23b9-4241-a15e-bba3c12a4085",
    "name": "Elsinore",
    "isFavourite": false,
    "image": "http://dummyimage.com/187x165.jpg/5fa2dd/ffffff",
    "groups": []
  },
  {
    "uuid": "ea5aa0fe-4f87-4c89-9814-fa5834782168",
    "name": "Nikoletta",
    "isFavourite": true,
    "image": "http://dummyimage.com/236x162.jpg/5fa2dd/ffffff",
    "groups": []
  },
  {
    "uuid": "acfdc460-8414-4f1b-babf-8dc1399d630c",
    "name": "Marissa",
    "isFavourite": true,
    "image": "http://dummyimage.com/240x247.png/ff4444/ffffff",
    "groups": []
  },
  {
    "uuid": "dc2f1087-ae40-47d3-833b-20104b5f2249",
    "name": "Brittni",
    "isFavourite": false,
    "image": "http://dummyimage.com/178x203.png/dddddd/000000",
    "groups": []
  },
  {
    "uuid": "8bd09cba-4320-4d78-8a64-6601486b679c",
    "name": "Tonye",
    "isFavourite": false,
    "image": "http://dummyimage.com/165x121.png/cc0000/ffffff",
    "groups": []
  },
  {
    "uuid": "43a8b73f-1719-4476-9c22-a3a11a896ed1",
    "name": "Sayre",
    "isFavourite": true,
    "image": "http://dummyimage.com/186x160.jpg/ff4444/ffffff",
    "groups": []
  },
  {
    "uuid": "ed40cffb-35af-48a1-a9c1-e42f456adbc9",
    "name": "Talbert",
    "isFavourite": false,
    "image": "http://dummyimage.com/169x139.png/cc0000/ffffff",
    "groups": []
  },
  {
    "uuid": "5770b6b6-ab7d-4439-a5dc-9cb1c265a7a9",
    "name": "Shantee",
    "isFavourite": true,
    "image": "http://dummyimage.com/247x242.png/dddddd/000000",
    "groups": []
  },
  {
    "uuid": "cc4a2717-88ec-4923-9002-cca395f01193",
    "name": "Valida",
    "isFavourite": true,
    "image": "http://dummyimage.com/180x221.png/dddddd/000000",
    "groups": []
  },
  {
    "uuid": "821fc1d4-0852-4295-a77d-778d495751eb",
    "name": "Avram",
    "isFavourite": true,
    "image": "http://dummyimage.com/142x156.bmp/dddddd/000000",
    "groups": []
  },
  {
    "uuid": "7f808e1c-7a47-43ca-b07d-fe545e1f7a9c",
    "name": "Lula",
    "isFavourite": true,
    "image": "http://dummyimage.com/136x110.png/5fa2dd/ffffff",
    "groups": []
  },
  {
    "uuid": "1d5b98de-aa6e-4e79-9f42-edb4fa4f2d1c",
    "name": "Karine",
    "isFavourite": true,
    "image": "http://dummyimage.com/101x110.bmp/5fa2dd/ffffff",
    "groups": []
  },
  {
    "uuid": "cccc0157-0c4d-45a8-85f5-b3be2ff53e59",
    "name": "Kissie",
    "isFavourite": false,
    "image": "http://dummyimage.com/190x104.png/dddddd/000000",
    "groups": []
  },
  {
    "uuid": "ea38d828-a5a4-4eb6-81b3-eb049a98e884",
    "name": "Janot",
    "isFavourite": true,
    "image": "http://dummyimage.com/139x179.jpg/dddddd/000000",
    "groups": []
  },
  {
    "uuid": "9b8a3992-5b68-4af4-bfd2-0e1b3f3daf78",
    "name": "Phil",
    "isFavourite": false,
    "image": "http://dummyimage.com/241x185.bmp/5fa2dd/ffffff",
    "groups": []
  },
  {
    "uuid": "2eed76a8-fc59-49cc-8d6a-4e2579c24825",
    "name": "Alvinia",
    "isFavourite": false,
    "image": "http://dummyimage.com/107x159.bmp/cc0000/ffffff",
    "groups": []
  },
  {
    "uuid": "b1a6ad7a-f750-4e09-a296-38f97a7a4aaf",
    "name": "Angele",
    "isFavourite": true,
    "image": "http://dummyimage.com/182x166.png/cc0000/ffffff",
    "groups": []
  },
  {
    "uuid": "35db8161-1aa6-45d5-ac16-2ddf6e68fee0",
    "name": "Lucky",
    "isFavourite": false,
    "image": "http://dummyimage.com/228x175.jpg/ff4444/ffffff",
    "groups": []
  },
  {
    "uuid": "d456ed1c-4b54-42d2-9fec-7733a9a22339",
    "name": "Goldy",
    "isFavourite": true,
    "image": "http://dummyimage.com/206x138.png/cc0000/ffffff",
    "groups": []
  },
  {
    "uuid": "9a52548c-7dab-4ccb-996d-69e8f3079f4e",
    "name": "Corine",
    "isFavourite": false,
    "image": "http://dummyimage.com/243x140.png/5fa2dd/ffffff",
    "groups": []
  },
  {
    "uuid": "66dc4533-4344-4ec1-8d73-4212a6c984bc",
    "name": "Francisca",
    "isFavourite": true,
    "image": "http://dummyimage.com/230x231.png/5fa2dd/ffffff",
    "groups": []
  },
  {
    "uuid": "bf1f5ab7-082a-48fd-9d97-e76947169d5c",
    "name": "Cecilio",
    "isFavourite": true,
    "image": "http://dummyimage.com/218x165.bmp/5fa2dd/ffffff",
    "groups": []
  },
  {
    "uuid": "4e933e57-9066-4c16-864f-76b352a3b5ab",
    "name": "Felicity",
    "isFavourite": true,
    "image": "http://dummyimage.com/140x104.png/5fa2dd/ffffff",
    "groups": []
  },
  {
    "uuid": "a0e9637c-61b3-44ec-8cd6-7047eae3c9ff",
    "name": "Garland",
    "isFavourite": true,
    "image": "http://dummyimage.com/120x145.jpg/5fa2dd/ffffff",
    "groups": []
  },
  {
    "uuid": "c0cb29cc-97a5-41cc-9945-99dbaa1a209a",
    "name": "Teodoro",
    "isFavourite": false,
    "image": "http://dummyimage.com/160x220.bmp/dddddd/000000",
    "groups": []
  },
  {
    "uuid": "8d773810-1bc1-4d5d-9838-ed9a2ae1de9f",
    "name": "Gamaliel",
    "isFavourite": false,
    "image": "http://dummyimage.com/178x133.jpg/cc0000/ffffff",
    "groups": []
  },
  {
    "uuid": "fc5af316-13be-4b28-939c-0936e3ec1086",
    "name": "Rosemonde",
    "isFavourite": false,
    "image": "http://dummyimage.com/183x111.bmp/5fa2dd/ffffff",
    "groups": []
  },
  {
    "uuid": "a236b860-933e-4109-8d62-f36e03f0c811",
    "name": "Eleen",
    "isFavourite": false,
    "image": "http://dummyimage.com/121x234.bmp/ff4444/ffffff",
    "groups": []
  },
  {
    "uuid": "f5e49844-3b1e-46eb-9340-cd8c3148930b",
    "name": "Pooh",
    "isFavourite": false,
    "image": "http://dummyimage.com/164x250.jpg/cc0000/ffffff",
    "groups": []
  },
  {
    "uuid": "4cecb6a3-922a-441c-87dd-4eac50a8bc27",
    "name": "Carole",
    "isFavourite": false,
    "image": "http://dummyimage.com/182x199.png/dddddd/000000",
    "groups": []
  },
  {
    "uuid": "72bb8b88-14ec-4fb5-a040-2d01001d5ed1",
    "name": "Petra",
    "isFavourite": true,
    "image": "http://dummyimage.com/135x208.png/ff4444/ffffff",
    "groups": []
  },
  {
    "uuid": "76f2f5f9-5efc-476f-bc6e-84b451fcf8b9",
    "name": "Norah",
    "isFavourite": true,
    "image": "http://dummyimage.com/139x178.jpg/5fa2dd/ffffff",
    "groups": []
  },
  {
    "uuid": "583ec432-183b-49f1-b954-8a483ffdaea8",
    "name": "Joelie",
    "isFavourite": false,
    "image": "http://dummyimage.com/152x131.jpg/5fa2dd/ffffff",
    "groups": []
  },
  {
    "uuid": "85b6d050-a074-46a9-81d7-4cb203e8a21d",
    "name": "Garik",
    "isFavourite": true,
    "image": "http://dummyimage.com/229x174.jpg/dddddd/000000",
    "groups": []
  },
  {
    "uuid": "394bab14-c8a7-42fd-8da2-ae1548558fae",
    "name": "Celesta",
    "isFavourite": true,
    "image": "http://dummyimage.com/124x139.bmp/5fa2dd/ffffff",
    "groups": []
  },
  {
    "uuid": "2cc8b501-305f-4330-8a50-f19d74b4ba5f",
    "name": "Olympe",
    "isFavourite": true,
    "image": "http://dummyimage.com/147x131.bmp/cc0000/ffffff",
    "groups": []
  },
  {
    "uuid": "8d34fe1f-9cd0-4ad8-b33e-44ae865d46bc",
    "name": "Bonnee",
    "isFavourite": false,
    "image": "http://dummyimage.com/201x105.bmp/dddddd/000000",
    "groups": []
  },
  {
    "uuid": "ec5448d7-573c-481a-9b38-0641416c32b3",
    "name": "Alexa",
    "isFavourite": true,
    "image": "http://dummyimage.com/106x157.jpg/5fa2dd/ffffff",
    "groups": []
  },
  {
    "uuid": "2187fd0d-baeb-43db-9ab2-b906f934fabe",
    "name": "Andi",
    "isFavourite": false,
    "image": "http://dummyimage.com/219x214.bmp/5fa2dd/ffffff",
    "groups": []
  },
  {
    "uuid": "4d49ac1b-24c3-499c-a937-f133b35bee2b",
    "name": "Harlan",
    "isFavourite": true,
    "image": "http://dummyimage.com/140x216.bmp/5fa2dd/ffffff",
    "groups": []
  },
  {
    "uuid": "ec90f70e-cdd8-493e-b78c-699570ebf886",
    "name": "Hyman",
    "isFavourite": true,
    "image": "http://dummyimage.com/134x165.jpg/dddddd/000000",
    "groups": []
  },
  {
    "uuid": "478d70cb-b018-43fc-8f70-bd3a16d60fcd",
    "name": "Niccolo",
    "isFavourite": true,
    "image": "http://dummyimage.com/250x115.bmp/5fa2dd/ffffff",
    "groups": []
  },
  {
    "uuid": "16b37b3b-8736-496b-a6a6-0260bef14e64",
    "name": "Delainey",
    "isFavourite": true,
    "image": "http://dummyimage.com/164x109.png/cc0000/ffffff",
    "groups": []
  },
  {
    "uuid": "962e4a3d-d2e9-4bc0-a6ea-f6a01607651e",
    "name": "Nestor",
    "isFavourite": true,
    "image": "http://dummyimage.com/158x130.bmp/dddddd/000000",
    "groups": []
  },
  {
    "uuid": "7d0ac0b1-fc0a-4d46-8d36-23739cbaaf00",
    "name": "My",
    "isFavourite": true,
    "image": "http://dummyimage.com/149x216.jpg/5fa2dd/ffffff",
    "groups": []
  },
  {
    "uuid": "535186cd-ba8d-4ddf-9d51-da1ccb3ec4c0",
    "name": "Celesta",
    "isFavourite": false,
    "image": "http://dummyimage.com/215x147.png/dddddd/000000",
    "groups": []
  },
  {
    "uuid": "e9ce5b4c-9e5c-4aff-9605-f3d23483dc2f",
    "name": "Kerwin",
    "isFavourite": true,
    "image": "http://dummyimage.com/211x229.bmp/5fa2dd/ffffff",
    "groups": []
  },
  {
    "uuid": "3aa82343-c236-4cfb-9ed5-5ccfe8fcece5",
    "name": "Ailis",
    "isFavourite": false,
    "image": "http://dummyimage.com/171x195.jpg/dddddd/000000",
    "groups": []
  },
  {
    "uuid": "839fc410-cb0b-400a-b842-bf0ac5bf7cde",
    "name": "Lara",
    "isFavourite": true,
    "image": "http://dummyimage.com/244x123.bmp/dddddd/000000",
    "groups": []
  },
  {
    "uuid": "658ed045-470e-4372-bf83-87f2a6067f34",
    "name": "Hastings",
    "isFavourite": true,
    "image": "http://dummyimage.com/191x160.png/5fa2dd/ffffff",
    "groups": []
  },
  {
    "uuid": "c08aa019-3630-427f-b5cb-f15715a8f9e7",
    "name": "Karilynn",
    "isFavourite": true,
    "image": "http://dummyimage.com/160x151.png/5fa2dd/ffffff",
    "groups": []
  },
  {
    "uuid": "c6353156-acdb-42d2-b368-375df064dfe1",
    "name": "Bank",
    "isFavourite": false,
    "image": "http://dummyimage.com/200x207.png/ff4444/ffffff",
    "groups": []
  },
  {
    "uuid": "5d9e4665-207a-4ae9-8f77-19d7e607e9cb",
    "name": "Olympe",
    "isFavourite": true,
    "image": "http://dummyimage.com/160x250.bmp/ff4444/ffffff",
    "groups": []
  },
  {
    "uuid": "15c28695-9a10-4b6f-abb5-64966c697d78",
    "name": "Moll",
    "isFavourite": true,
    "image": "http://dummyimage.com/111x136.bmp/cc0000/ffffff",
    "groups": []
  },
  {
    "uuid": "dc20f6f4-d3cf-4969-8240-cf06c058e9fc",
    "name": "Tait",
    "isFavourite": false,
    "image": "http://dummyimage.com/239x108.jpg/ff4444/ffffff",
    "groups": []
  },
  {
    "uuid": "c19abdd7-6aeb-4fee-ac73-82bda9029f13",
    "name": "Chantal",
    "isFavourite": false,
    "image": "http://dummyimage.com/226x245.png/ff4444/ffffff",
    "groups": []
  },
  {
    "uuid": "f50a07e4-cb57-4f82-8112-ccf581271289",
    "name": "Donall",
    "isFavourite": false,
    "image": "http://dummyimage.com/179x112.png/5fa2dd/ffffff",
    "groups": []
  },
  {
    "uuid": "ec0a96bb-bb46-4b35-885b-2b88251a7b5b",
    "name": "Krishna",
    "isFavourite": false,
    "image": "http://dummyimage.com/152x240.jpg/ff4444/ffffff",
    "groups": []
  },
  {
    "uuid": "b99fb731-778d-4350-81d9-b02e84f702c8",
    "name": "Murray",
    "isFavourite": true,
    "image": "http://dummyimage.com/187x131.bmp/5fa2dd/ffffff",
    "groups": []
  },
  {
    "uuid": "a3ba6e5b-15a6-4bf3-b0c6-cb9b7693ba49",
    "name": "Kessiah",
    "isFavourite": true,
    "image": "http://dummyimage.com/121x188.bmp/5fa2dd/ffffff",
    "groups": []
  },
  {
    "uuid": "8ffc899e-dde9-4c87-9889-636164a89d50",
    "name": "Tamas",
    "isFavourite": true,
    "image": "http://dummyimage.com/151x246.bmp/dddddd/000000",
    "groups": []
  },
  {
    "uuid": "eabbc098-7b22-408c-9224-f015f0dbfae2",
    "name": "Zak",
    "isFavourite": false,
    "image": "http://dummyimage.com/109x210.png/cc0000/ffffff",
    "groups": []
  },
  {
    "uuid": "d11d02b4-aa0c-47a8-9ae1-70a0751b814d",
    "name": "Naomi",
    "isFavourite": false,
    "image": "http://dummyimage.com/221x213.jpg/5fa2dd/ffffff",
    "groups": []
  },
  {
    "uuid": "9888e859-e6bf-49c7-aef8-19b45e2ad3b4",
    "name": "Xenos",
    "isFavourite": true,
    "image": "http://dummyimage.com/210x143.png/dddddd/000000",
    "groups": []
  },
  {
    "uuid": "969dcf99-626f-415c-a79a-d14723789a49",
    "name": "Cheri",
    "isFavourite": false,
    "image": "http://dummyimage.com/237x173.bmp/dddddd/000000",
    "groups": []
  },
  {
    "uuid": "c4a92b04-a11b-47db-95bb-df86d3946dfa",
    "name": "Rourke",
    "isFavourite": false,
    "image": "http://dummyimage.com/103x129.jpg/ff4444/ffffff",
    "groups": []
  },
  {
    "uuid": "421c3ae7-b5ad-462d-bf7f-5a31eed1695d",
    "name": "Rutger",
    "isFavourite": false,
    "image": "http://dummyimage.com/133x188.jpg/5fa2dd/ffffff",
    "groups": []
  },
  {
    "uuid": "f5d3a493-ff17-4ef2-b3cd-35723dcefb85",
    "name": "Moyna",
    "isFavourite": true,
    "image": "http://dummyimage.com/142x200.jpg/dddddd/000000",
    "groups": []
  },
  {
    "uuid": "6e688666-98c5-439a-b76b-8412d3b93c4c",
    "name": "Clio",
    "isFavourite": true,
    "image": "http://dummyimage.com/222x151.bmp/5fa2dd/ffffff",
    "groups": []
  },
  {
    "uuid": "8a57de12-e84c-4c4f-9957-6d4783467d7c",
    "name": "Nelson",
    "isFavourite": false,
    "image": "http://dummyimage.com/120x191.png/dddddd/000000",
    "groups": []
  },
  {
    "uuid": "ed145d9e-60c6-4b01-9b05-18e9d3fd15f4",
    "name": "Thekla",
    "isFavourite": true,
    "image": "http://dummyimage.com/223x143.jpg/5fa2dd/ffffff",
    "groups": []
  },
  {
    "uuid": "9b0589ad-ba1a-4a25-a9c3-141930f79c6b",
    "name": "Correy",
    "isFavourite": false,
    "image": "http://dummyimage.com/212x244.jpg/ff4444/ffffff",
    "groups": []
  },
  {
    "uuid": "2ce52f90-8060-4201-b5bb-eea1f5281938",
    "name": "Corrinne",
    "isFavourite": true,
    "image": "http://dummyimage.com/160x219.png/ff4444/ffffff",
    "groups": []
  },
  {
    "uuid": "f1422195-7fed-4009-b404-95e5605894b7",
    "name": "Letti",
    "isFavourite": false,
    "image": "http://dummyimage.com/171x222.png/dddddd/000000",
    "groups": []
  },
  {
    "uuid": "0421d64a-43b1-4d93-80a3-62acb50738a6",
    "name": "Lorene",
    "isFavourite": false,
    "image": "http://dummyimage.com/189x247.jpg/ff4444/ffffff",
    "groups": []
  },
  {
    "uuid": "a390ee2a-9c87-47ed-9275-ca1ed8da5b8f",
    "name": "Tedra",
    "isFavourite": true,
    "image": "http://dummyimage.com/122x133.bmp/cc0000/ffffff",
    "groups": []
  },
  {
    "uuid": "3c361cf9-f92d-4da2-9e4f-bac01d30eda9",
    "name": "Ella",
    "isFavourite": true,
    "image": "http://dummyimage.com/101x120.jpg/ff4444/ffffff",
    "groups": []
  },
  {
    "uuid": "3ed3033f-9de1-4a5f-9962-d5c54293370a",
    "name": "Kirk",
    "isFavourite": true,
    "image": "http://dummyimage.com/181x187.png/dddddd/000000",
    "groups": []
  },
  {
    "uuid": "ead323f8-fc68-4f39-a6e3-20ba6279c2ee",
    "name": "Brandy",
    "isFavourite": false,
    "image": "http://dummyimage.com/103x155.bmp/dddddd/000000",
    "groups": []
  },
  {
    "uuid": "beaaa2a3-41dc-4ac9-a49d-1ef3cf0f4993",
    "name": "Kimble",
    "isFavourite": true,
    "image": "http://dummyimage.com/201x222.bmp/5fa2dd/ffffff",
    "groups": []
  },
  {
    "uuid": "ebf9896f-8780-4cee-8a7a-328cb230a032",
    "name": "Vin",
    "isFavourite": false,
    "image": "http://dummyimage.com/247x101.jpg/ff4444/ffffff",
    "groups": []
  },
  {
    "uuid": "9e7703d1-1eae-40a2-92ff-806aa8aba076",
    "name": "Broddy",
    "isFavourite": false,
    "image": "http://dummyimage.com/192x231.jpg/cc0000/ffffff",
    "groups": []
  },
  {
    "uuid": "48e3bef3-8c69-43a5-a3ad-03b5bed64d35",
    "name": "Micheal",
    "isFavourite": true,
    "image": "http://dummyimage.com/238x141.bmp/cc0000/ffffff",
    "groups": []
  },
  {
    "uuid": "9ac89bfe-8f55-48f9-89f2-c48a1e92b180",
    "name": "Josias",
    "isFavourite": false,
    "image": "http://dummyimage.com/200x117.jpg/cc0000/ffffff",
    "groups": []
  },
  {
    "uuid": "f55d3c74-acf0-452f-a38a-4afd489f8e21",
    "name": "Fredi",
    "isFavourite": false,
    "image": "http://dummyimage.com/241x241.bmp/cc0000/ffffff",
    "groups": []
  },
  {
    "uuid": "65fc2675-d6c4-4588-9eb4-a95da496f12a",
    "name": "Bambi",
    "isFavourite": false,
    "image": "http://dummyimage.com/172x225.jpg/ff4444/ffffff",
    "groups": []
  },
  {
    "uuid": "ed2b72e6-b453-4c9b-983c-5316648ff45b",
    "name": "Albert",
    "isFavourite": true,
    "image": "http://dummyimage.com/124x217.bmp/dddddd/000000",
    "groups": []
  },
  {
    "uuid": "64f7c28a-7803-4940-b114-3c84d3ec61ce",
    "name": "Vlad",
    "isFavourite": true,
    "image": "http://dummyimage.com/166x245.jpg/dddddd/000000",
    "groups": []
  },
  {
    "uuid": "5e3f922e-2c93-4a43-b242-7345fe40e46a",
    "name": "Timmi",
    "isFavourite": false,
    "image": "http://dummyimage.com/175x136.png/5fa2dd/ffffff",
    "groups": []
  },
  {
    "uuid": "b3303a1c-2484-4c20-86c5-e94ef2e3dca3",
    "name": "Berti",
    "isFavourite": false,
    "image": "http://dummyimage.com/137x143.bmp/ff4444/ffffff",
    "groups": []
  },
  {
    "uuid": "e55ec692-1167-436e-9ad5-fe01273146ae",
    "name": "Sibbie",
    "isFavourite": false,
    "image": "http://dummyimage.com/163x189.bmp/dddddd/000000",
    "groups": []
  },
  {
    "uuid": "f64ec9b6-f74d-4e9b-a1be-267a2dfeeca6",
    "name": "Layney",
    "isFavourite": false,
    "image": "http://dummyimage.com/183x139.jpg/5fa2dd/ffffff",
    "groups": []
  },
  {
    "uuid": "5bf5afca-e7e9-4292-96e0-e79ac21cdb3b",
    "name": "Salome",
    "isFavourite": true,
    "image": "http://dummyimage.com/211x248.png/ff4444/ffffff",
    "groups": []
  },
  {
    "uuid": "d7995ede-da53-4bc0-bb38-83dd6d2a9f08",
    "name": "Matias",
    "isFavourite": false,
    "image": "http://dummyimage.com/165x215.jpg/cc0000/ffffff",
    "groups": []
  },
  {
    "uuid": "bda22e25-a218-4d87-ac56-be5fb82982b3",
    "name": "Ali",
    "isFavourite": false,
    "image": "http://dummyimage.com/166x188.bmp/5fa2dd/ffffff",
    "groups": []
  },
  {
    "uuid": "9350bae0-21c5-4341-bf57-a7d65e7c5ddf",
    "name": "Dag",
    "isFavourite": true,
    "image": "http://dummyimage.com/171x108.jpg/ff4444/ffffff",
    "groups": []
  },
  {
    "uuid": "2e3f4ca4-8759-4fde-9d24-c482ce9bf21e",
    "name": "Bernadine",
    "isFavourite": true,
    "image": "http://dummyimage.com/207x111.png/cc0000/ffffff",
    "groups": []
  },
  {
    "uuid": "ab6a86ac-b5d4-43ff-820c-11f2321eaa90",
    "name": "Wenda",
    "isFavourite": true,
    "image": "http://dummyimage.com/163x104.bmp/cc0000/ffffff",
    "groups": []
  },
  {
    "uuid": "a615a522-3ec4-4f80-b7a6-0bbabe3613c1",
    "name": "Kelila",
    "isFavourite": true,
    "image": "http://dummyimage.com/124x223.png/5fa2dd/ffffff",
    "groups": []
  },
  {
    "uuid": "9acd3f8f-466c-4a06-99a6-abe2351f9648",
    "name": "Faina",
    "isFavourite": false,
    "image": "http://dummyimage.com/187x106.jpg/cc0000/ffffff",
    "groups": []
  },
  {
    "uuid": "73e43d48-d8b1-4699-838a-7fc335cb61dc",
    "name": "Ellene",
    "isFavourite": true,
    "image": "http://dummyimage.com/139x176.png/ff4444/ffffff",
    "groups": []
  },
  {
    "uuid": "87ba4b07-9a0f-42f4-afdb-801d39e42822",
    "name": "Lothaire",
    "isFavourite": false,
    "image": "http://dummyimage.com/156x205.jpg/cc0000/ffffff",
    "groups": []
  },
  {
    "uuid": "0c848796-1709-4749-846f-b552916dd6c5",
    "name": "Kylie",
    "isFavourite": false,
    "image": "http://dummyimage.com/232x138.jpg/cc0000/ffffff",
    "groups": []
  },
  {
    "uuid": "f41956aa-8e83-4e25-af8a-0246202cdf11",
    "name": "Alair",
    "isFavourite": false,
    "image": "http://dummyimage.com/115x109.jpg/ff4444/ffffff",
    "groups": []
  },
  {
    "uuid": "5b44da69-28be-4fb4-83e1-7fcf5b146e6c",
    "name": "Clemmy",
    "isFavourite": true,
    "image": "http://dummyimage.com/246x103.png/5fa2dd/ffffff",
    "groups": []
  },
  {
    "uuid": "79226fa1-ff01-4e30-8488-7360bfbcfd23",
    "name": "Ryun",
    "isFavourite": false,
    "image": "http://dummyimage.com/148x243.png/ff4444/ffffff",
    "groups": []
  },
  {
    "uuid": "0ebc2471-bc98-48d2-854a-19c0e5c7e6a2",
    "name": "Hall",
    "isFavourite": false,
    "image": "http://dummyimage.com/184x224.bmp/dddddd/000000",
    "groups": []
  },
  {
    "uuid": "d2e29809-220a-4f2a-b755-f57a88e1cb80",
    "name": "Heinrick",
    "isFavourite": true,
    "image": "http://dummyimage.com/249x215.png/cc0000/ffffff",
    "groups": []
  },
  {
    "uuid": "00e4b316-2235-431b-8454-b2597056e8cc",
    "name": "Maria",
    "isFavourite": false,
    "image": "http://dummyimage.com/109x175.bmp/5fa2dd/ffffff",
    "groups": []
  },
  {
    "uuid": "314dcc50-4699-4a69-8b7d-77664b9a6ef4",
    "name": "Susanne",
    "isFavourite": false,
    "image": "http://dummyimage.com/137x132.png/dddddd/000000",
    "groups": []
  },
  {
    "uuid": "6c757181-8df6-42f4-ae9a-25f471b3e3cb",
    "name": "Juanita",
    "isFavourite": true,
    "image": "http://dummyimage.com/130x213.bmp/ff4444/ffffff",
    "groups": []
  },
  {
    "uuid": "8939d6f3-9993-4346-ab97-7345baf88d22",
    "name": "Ivan",
    "isFavourite": true,
    "image": "http://dummyimage.com/212x245.jpg/ff4444/ffffff",
    "groups": []
  },
  {
    "uuid": "598177a1-6825-4a9b-a184-106237dcb09a",
    "name": "Herc",
    "isFavourite": true,
    "image": "http://dummyimage.com/200x189.jpg/dddddd/000000",
    "groups": []
  },
  {
    "uuid": "66ae7034-b93b-4012-aec9-a35fff7f83cb",
    "name": "Kenneth",
    "isFavourite": true,
    "image": "http://dummyimage.com/193x176.bmp/ff4444/ffffff",
    "groups": []
  },
  {
    "uuid": "c2de4a96-e0cd-409a-acde-ccc028b60b51",
    "name": "Bonita",
    "isFavourite": true,
    "image": "http://dummyimage.com/186x196.png/5fa2dd/ffffff",
    "groups": []
  },
  {
    "uuid": "e93ccfc4-b9a3-4471-bac9-79db4940a8a7",
    "name": "Miguela",
    "isFavourite": true,
    "image": "http://dummyimage.com/135x181.bmp/ff4444/ffffff",
    "groups": []
  },
  {
    "uuid": "c147f518-54f5-4c93-b035-97d1071eec10",
    "name": "Parry",
    "isFavourite": true,
    "image": "http://dummyimage.com/134x232.png/dddddd/000000",
    "groups": []
  },
  {
    "uuid": "9f51012f-137b-4687-9ede-1abf5ae4bfa8",
    "name": "Cesar",
    "isFavourite": false,
    "image": "http://dummyimage.com/162x106.jpg/cc0000/ffffff",
    "groups": []
  },
  {
    "uuid": "22fe2667-08d8-4e69-81b3-8cc63759cde8",
    "name": "Jaine",
    "isFavourite": false,
    "image": "http://dummyimage.com/152x216.bmp/cc0000/ffffff",
    "groups": []
  },
  {
    "uuid": "942730b1-a100-4c1e-9659-f51b2f3ea3b9",
    "name": "Hilda",
    "isFavourite": true,
    "image": "http://dummyimage.com/144x171.jpg/5fa2dd/ffffff",
    "groups": []
  },
  {
    "uuid": "7020a8ec-ebbd-4dd3-a44b-3d6f7da275b1",
    "name": "Darrick",
    "isFavourite": true,
    "image": "http://dummyimage.com/198x210.png/5fa2dd/ffffff",
    "groups": []
  },
  {
    "uuid": "41412c37-721f-4dd6-aa64-ac3786d579b8",
    "name": "Caitrin",
    "isFavourite": true,
    "image": "http://dummyimage.com/133x119.bmp/dddddd/000000",
    "groups": []
  },
  {
    "uuid": "b88178e4-55c3-472e-b47b-5d7eee8b696c",
    "name": "Annabel",
    "isFavourite": false,
    "image": "http://dummyimage.com/173x122.bmp/cc0000/ffffff",
    "groups": []
  },
  {
    "uuid": "eac45fa6-36fa-429c-a40e-3653da0ad254",
    "name": "Abbott",
    "isFavourite": false,
    "image": "http://dummyimage.com/196x104.png/dddddd/000000",
    "groups": []
  },
  {
    "uuid": "dd702c79-4bce-480d-abf2-50285579333c",
    "name": "Erminia",
    "isFavourite": true,
    "image": "http://dummyimage.com/115x127.png/cc0000/ffffff",
    "groups": []
  },
  {
    "uuid": "81ef7fa5-b964-4b52-9d8d-3f632b17bdef",
    "name": "Kerk",
    "isFavourite": false,
    "image": "http://dummyimage.com/184x189.jpg/5fa2dd/ffffff",
    "groups": []
  },
  {
    "uuid": "6d96c1c8-3b38-4e03-bd3a-17d0d3f0fa54",
    "name": "Spence",
    "isFavourite": false,
    "image": "http://dummyimage.com/238x242.jpg/cc0000/ffffff",
    "groups": []
  },
  {
    "uuid": "67b33374-209f-418c-b027-7b2e94b043ea",
    "name": "Isak",
    "isFavourite": true,
    "image": "http://dummyimage.com/159x181.bmp/ff4444/ffffff",
    "groups": []
  },
  {
    "uuid": "ad1927e4-e00c-4784-9965-67e8f0ceb3f6",
    "name": "Kenneth",
    "isFavourite": true,
    "image": "http://dummyimage.com/180x168.bmp/5fa2dd/ffffff",
    "groups": []
  },
  {
    "uuid": "042d89e1-3019-4f90-9cc9-c61022c6dbf5",
    "name": "Waring",
    "isFavourite": false,
    "image": "http://dummyimage.com/218x244.png/cc0000/ffffff",
    "groups": []
  },
  {
    "uuid": "152f5d7d-befc-4d17-a085-0af9d5f6c42d",
    "name": "Feliza",
    "isFavourite": false,
    "image": "http://dummyimage.com/226x236.png/cc0000/ffffff",
    "groups": []
  },
  {
    "uuid": "075ebecf-2f64-4bb5-943a-a0cdc8676dd3",
    "name": "Maurise",
    "isFavourite": false,
    "image": "http://dummyimage.com/130x193.png/cc0000/ffffff",
    "groups": []
  },
  {
    "uuid": "b96e70db-143f-41ed-99b2-898864a66ae4",
    "name": "Cece",
    "isFavourite": true,
    "image": "http://dummyimage.com/111x240.png/dddddd/000000",
    "groups": []
  },
  {
    "uuid": "006f9db5-609b-47a9-9968-650bfce70dce",
    "name": "Wadsworth",
    "isFavourite": true,
    "image": "http://dummyimage.com/202x194.png/cc0000/ffffff",
    "groups": []
  },
  {
    "uuid": "a3a741f0-0006-44a5-a5d5-6cfa9b3fdda0",
    "name": "Alasteir",
    "isFavourite": false,
    "image": "http://dummyimage.com/193x243.jpg/cc0000/ffffff",
    "groups": []
  },
  {
    "uuid": "1945db8e-cd41-451e-9049-470d404c02f1",
    "name": "Gorden",
    "isFavourite": false,
    "image": "http://dummyimage.com/218x109.bmp/cc0000/ffffff",
    "groups": []
  },
  {
    "uuid": "be1e7df7-7ce3-45b8-af4d-0a1b445595c6",
    "name": "Jess",
    "isFavourite": false,
    "image": "http://dummyimage.com/192x139.png/5fa2dd/ffffff",
    "groups": []
  },
  {
    "uuid": "774c2aa2-7c14-4e16-802d-ce5b6fe188ca",
    "name": "Helli",
    "isFavourite": false,
    "image": "http://dummyimage.com/146x203.bmp/cc0000/ffffff",
    "groups": []
  },
  {
    "uuid": "f3cd5831-19a2-4499-9313-78853eccf849",
    "name": "Virgilio",
    "isFavourite": false,
    "image": "http://dummyimage.com/198x165.jpg/cc0000/ffffff",
    "groups": []
  },
  {
    "uuid": "1a22db89-b80c-4a81-9ec5-a35eeb32fe58",
    "name": "Marge",
    "isFavourite": true,
    "image": "http://dummyimage.com/157x113.bmp/5fa2dd/ffffff",
    "groups": []
  },
  {
    "uuid": "0892c77a-6802-4e0c-8de6-89cc24abe0f1",
    "name": "Shel",
    "isFavourite": false,
    "image": "http://dummyimage.com/158x121.png/5fa2dd/ffffff",
    "groups": []
  },
  {
    "uuid": "6b98b198-1abc-4c2d-802e-d8d4e3c63b22",
    "name": "Ignazio",
    "isFavourite": true,
    "image": "http://dummyimage.com/175x139.jpg/ff4444/ffffff",
    "groups": []
  },
  {
    "uuid": "f93733f1-54a1-41d0-a88d-e44881707bbc",
    "name": "Velma",
    "isFavourite": true,
    "image": "http://dummyimage.com/167x152.png/dddddd/000000",
    "groups": []
  },
  {
    "uuid": "917e2430-9bf7-4ac4-a241-b77b722934d1",
    "name": "Trace",
    "isFavourite": false,
    "image": "http://dummyimage.com/118x193.bmp/cc0000/ffffff",
    "groups": []
  },
  {
    "uuid": "ff4bbe89-dda6-4068-9387-79ee6a21b053",
    "name": "Richard",
    "isFavourite": true,
    "image": "http://dummyimage.com/193x148.bmp/cc0000/ffffff",
    "groups": []
  },
  {
    "uuid": "f8eaf90d-0fc9-42a8-a391-5d0a9f1dcb8d",
    "name": "Quinn",
    "isFavourite": false,
    "image": "http://dummyimage.com/212x105.bmp/dddddd/000000",
    "groups": []
  },
  {
    "uuid": "542e3026-3d69-46b1-9a40-3fab706fa802",
    "name": "Berry",
    "isFavourite": true,
    "image": "http://dummyimage.com/217x217.bmp/5fa2dd/ffffff",
    "groups": []
  },
  {
    "uuid": "d42f7dbd-9da5-4886-8073-0215c0dc8ea3",
    "name": "Nero",
    "isFavourite": true,
    "image": "http://dummyimage.com/130x128.png/dddddd/000000",
    "groups": []
  },
  {
    "uuid": "f5236e47-b3ea-4e1f-9a26-8974a3c6412b",
    "name": "Raviv",
    "isFavourite": true,
    "image": "http://dummyimage.com/116x113.bmp/5fa2dd/ffffff",
    "groups": []
  },
  {
    "uuid": "44be1382-e63c-41c4-8d77-c70c2f6703d7",
    "name": "Padget",
    "isFavourite": false,
    "image": "http://dummyimage.com/226x239.png/5fa2dd/ffffff",
    "groups": []
  },
  {
    "uuid": "818a8504-89e0-45b3-a42a-b6f63f77200e",
    "name": "Lenee",
    "isFavourite": false,
    "image": "http://dummyimage.com/106x180.jpg/cc0000/ffffff",
    "groups": []
  },
  {
    "uuid": "5174d16d-d6ca-4871-bb87-ddb1d80577ce",
    "name": "Miriam",
    "isFavourite": false,
    "image": "http://dummyimage.com/207x168.bmp/dddddd/000000",
    "groups": []
  },
  {
    "uuid": "93e7f0a1-8a51-49c8-9ebf-f1c165493f31",
    "name": "Maison",
    "isFavourite": true,
    "image": "http://dummyimage.com/113x123.jpg/cc0000/ffffff",
    "groups": []
  },
  {
    "uuid": "69155ae9-5d31-4027-b7bf-8f93da171b3c",
    "name": "Kimberly",
    "isFavourite": true,
    "image": "http://dummyimage.com/211x237.bmp/ff4444/ffffff",
    "groups": []
  },
  {
    "uuid": "a41745b5-c5f4-4108-aefb-88627e008a97",
    "name": "Rafaellle",
    "isFavourite": true,
    "image": "http://dummyimage.com/125x145.bmp/5fa2dd/ffffff",
    "groups": []
  },
  {
    "uuid": "10b731cc-b04a-4717-8f52-731442016e56",
    "name": "Myrle",
    "isFavourite": true,
    "image": "http://dummyimage.com/138x119.jpg/cc0000/ffffff",
    "groups": []
  },
  {
    "uuid": "2e435c4f-8f2a-421f-990d-73f48f122c4e",
    "name": "Berke",
    "isFavourite": false,
    "image": "http://dummyimage.com/142x134.bmp/cc0000/ffffff",
    "groups": []
  },
  {
    "uuid": "dc6025ad-76b5-4938-bc2b-afc029726f90",
    "name": "Tammara",
    "isFavourite": true,
    "image": "http://dummyimage.com/180x140.bmp/dddddd/000000",
    "groups": []
  },
  {
    "uuid": "c9f0d5f1-efd7-417f-aa13-b040eee30ef6",
    "name": "Bride",
    "isFavourite": true,
    "image": "http://dummyimage.com/209x106.png/5fa2dd/ffffff",
    "groups": []
  },
  {
    "uuid": "1b41dee3-1a18-41c3-b4cb-7bb926cbc123",
    "name": "Farrel",
    "isFavourite": false,
    "image": "http://dummyimage.com/212x166.png/dddddd/000000",
    "groups": []
  },
  {
    "uuid": "827140d4-9de0-48fe-92d6-423edcf0fb67",
    "name": "Giuditta",
    "isFavourite": false,
    "image": "http://dummyimage.com/231x152.jpg/dddddd/000000",
    "groups": []
  },
  {
    "uuid": "807a3d5e-ea7b-4979-86c2-54e7f5822a36",
    "name": "Inna",
    "isFavourite": true,
    "image": "http://dummyimage.com/113x242.bmp/cc0000/ffffff",
    "groups": []
  },
  {
    "uuid": "4efe91c2-c22d-4d2c-9435-33aaae71f330",
    "name": "Gabbie",
    "isFavourite": true,
    "image": "http://dummyimage.com/157x239.png/ff4444/ffffff",
    "groups": []
  },
  {
    "uuid": "aa60514e-08aa-4c81-9ce2-525807ac7074",
    "name": "Krystal",
    "isFavourite": false,
    "image": "http://dummyimage.com/207x191.bmp/cc0000/ffffff",
    "groups": []
  },
  {
    "uuid": "2672738f-a02b-440d-af07-3ab8a9709c6d",
    "name": "Sharon",
    "isFavourite": false,
    "image": "http://dummyimage.com/162x194.jpg/5fa2dd/ffffff",
    "groups": []
  },
  {
    "uuid": "18ce5ae2-9116-4baa-bc3e-360622007f86",
    "name": "Concettina",
    "isFavourite": false,
    "image": "http://dummyimage.com/171x132.bmp/cc0000/ffffff",
    "groups": []
  },
  {
    "uuid": "9666c363-e584-4aa5-892e-0404fde6f18a",
    "name": "Sean",
    "isFavourite": true,
    "image": "http://dummyimage.com/238x204.jpg/dddddd/000000",
    "groups": []
  },
  {
    "uuid": "7e26572c-54ab-4246-84a1-ec1517f3f609",
    "name": "Alfons",
    "isFavourite": false,
    "image": "http://dummyimage.com/208x143.bmp/ff4444/ffffff",
    "groups": []
  },
  {
    "uuid": "f5fa086f-5526-4def-b78e-131379189116",
    "name": "Christan",
    "isFavourite": true,
    "image": "http://dummyimage.com/245x183.bmp/ff4444/ffffff",
    "groups": []
  },
  {
    "uuid": "a11afeb5-804a-4538-a393-da7b2946c14c",
    "name": "Blaine",
    "isFavourite": true,
    "image": "http://dummyimage.com/151x143.bmp/cc0000/ffffff",
    "groups": []
  },
  {
    "uuid": "f28b5721-6ce7-47c2-8e75-8aae746191e6",
    "name": "Gwenny",
    "isFavourite": false,
    "image": "http://dummyimage.com/117x178.png/ff4444/ffffff",
    "groups": []
  },
  {
    "uuid": "ec63524d-5e4a-44dd-8f4f-a576410efa06",
    "name": "Marty",
    "isFavourite": true,
    "image": "http://dummyimage.com/225x216.jpg/dddddd/000000",
    "groups": []
  },
  {
    "uuid": "bfb1d190-ed96-409f-b150-7702d645b540",
    "name": "Yehudit",
    "isFavourite": false,
    "image": "http://dummyimage.com/141x244.png/cc0000/ffffff",
    "groups": []
  },
  {
    "uuid": "32854fea-1581-488d-9446-0e8f6728ccd3",
    "name": "Man",
    "isFavourite": false,
    "image": "http://dummyimage.com/173x195.bmp/cc0000/ffffff",
    "groups": []
  },
  {
    "uuid": "56a04bbe-1018-41a4-a7ad-c9d960780810",
    "name": "Yuri",
    "isFavourite": false,
    "image": "http://dummyimage.com/220x110.jpg/5fa2dd/ffffff",
    "groups": []
  },
  {
    "uuid": "5949b47d-6c5a-4c2c-82d5-46eda512da85",
    "name": "Camey",
    "isFavourite": true,
    "image": "http://dummyimage.com/190x101.jpg/dddddd/000000",
    "groups": []
  },
  {
    "uuid": "8fcd0a38-91ea-4b01-860b-3fa6c6c70270",
    "name": "Heidie",
    "isFavourite": false,
    "image": "http://dummyimage.com/193x127.bmp/5fa2dd/ffffff",
    "groups": []
  },
  {
    "uuid": "f3fd31ef-81a1-4808-8604-bb76f1d09c9b",
    "name": "Lida",
    "isFavourite": true,
    "image": "http://dummyimage.com/174x167.jpg/5fa2dd/ffffff",
    "groups": []
  },
  {
    "uuid": "aa518f28-2497-453b-9bb0-1b95bdb3f059",
    "name": "Bay",
    "isFavourite": true,
    "image": "http://dummyimage.com/239x123.bmp/cc0000/ffffff",
    "groups": []
  },
  {
    "uuid": "42a08b4e-c61d-4d7d-8d5f-4c98e5904524",
    "name": "Amelie",
    "isFavourite": true,
    "image": "http://dummyimage.com/134x241.png/dddddd/000000",
    "groups": []
  },
  {
    "uuid": "7d51a445-3f1e-40df-bd52-bac7ea4b2486",
    "name": "Gilberte",
    "isFavourite": true,
    "image": "http://dummyimage.com/232x160.png/5fa2dd/ffffff",
    "groups": []
  },
  {
    "uuid": "f7202f84-219f-4b48-a880-dd328eb6a0bb",
    "name": "Andonis",
    "isFavourite": true,
    "image": "http://dummyimage.com/178x176.png/dddddd/000000",
    "groups": []
  },
  {
    "uuid": "14592113-9745-418c-a1fe-dec1b49f6e53",
    "name": "Trudy",
    "isFavourite": false,
    "image": "http://dummyimage.com/120x163.bmp/cc0000/ffffff",
    "groups": []
  },
  {
    "uuid": "85acd47b-b7d6-4749-8bf3-4e53300b8ca2",
    "name": "Patrizia",
    "isFavourite": false,
    "image": "http://dummyimage.com/239x121.jpg/dddddd/000000",
    "groups": []
  },
  {
    "uuid": "206d248c-b72c-4d57-a739-bb98f47ee0a8",
    "name": "Stanwood",
    "isFavourite": true,
    "image": "http://dummyimage.com/205x183.png/5fa2dd/ffffff",
    "groups": []
  },
  {
    "uuid": "225260ce-f025-4249-8338-15f64dcd7828",
    "name": "Corey",
    "isFavourite": true,
    "image": "http://dummyimage.com/116x189.png/ff4444/ffffff",
    "groups": []
  },
  {
    "uuid": "b2093d29-b7e0-479b-b9cb-00e2e1112e02",
    "name": "Franklyn",
    "isFavourite": false,
    "image": "http://dummyimage.com/161x236.png/dddddd/000000",
    "groups": []
  },
  {
    "uuid": "fa870a32-e9ee-42ec-82d3-96cd9ae6b5e0",
    "name": "Devonne",
    "isFavourite": true,
    "image": "http://dummyimage.com/223x113.bmp/5fa2dd/ffffff",
    "groups": []
  },
  {
    "uuid": "8653791f-5b43-4a51-af85-d26a8ef32ae4",
    "name": "Almire",
    "isFavourite": true,
    "image": "http://dummyimage.com/243x135.bmp/ff4444/ffffff",
    "groups": []
  },
  {
    "uuid": "436b32a0-8fb7-41bd-96f8-030b7b4e580d",
    "name": "Dawn",
    "isFavourite": false,
    "image": "http://dummyimage.com/154x195.png/5fa2dd/ffffff",
    "groups": []
  },
  {
    "uuid": "7688cdd5-976d-4aee-8da3-d803ff14fc14",
    "name": "Krystyna",
    "isFavourite": false,
    "image": "http://dummyimage.com/130x235.bmp/dddddd/000000",
    "groups": []
  },
  {
    "uuid": "c33531b3-e760-4fbc-9a5b-5c0bdfb9985d",
    "name": "Kizzie",
    "isFavourite": true,
    "image": "http://dummyimage.com/186x247.bmp/5fa2dd/ffffff",
    "groups": []
  },
  {
    "uuid": "8184a3cd-dff4-4780-8d6d-8afb35807e6d",
    "name": "Shaine",
    "isFavourite": false,
    "image": "http://dummyimage.com/231x226.png/dddddd/000000",
    "groups": []
  },
  {
    "uuid": "184e5d26-b3c8-4919-a596-6e8cf4c5b369",
    "name": "Boyd",
    "isFavourite": true,
    "image": "http://dummyimage.com/112x203.png/dddddd/000000",
    "groups": []
  },
  {
    "uuid": "dd0f84b9-4030-4773-bdb9-55f34a8406b0",
    "name": "Shelagh",
    "isFavourite": true,
    "image": "http://dummyimage.com/155x138.png/5fa2dd/ffffff",
    "groups": []
  },
  {
    "uuid": "ef4275ab-6879-40bf-bb87-70f238dd510d",
    "name": "Vinny",
    "isFavourite": true,
    "image": "http://dummyimage.com/245x197.png/ff4444/ffffff",
    "groups": []
  },
  {
    "uuid": "8d4736b4-25a7-45f6-b49b-22347e915b87",
    "name": "Dewain",
    "isFavourite": false,
    "image": "http://dummyimage.com/151x225.bmp/5fa2dd/ffffff",
    "groups": []
  },
  {
    "uuid": "5752ae5e-c9b4-4acf-9b77-acbdd42ab1a8",
    "name": "Leena",
    "isFavourite": true,
    "image": "http://dummyimage.com/214x228.bmp/ff4444/ffffff",
    "groups": []
  },
  {
    "uuid": "d7534d9b-2d92-46d3-b810-14e0c0e7b48f",
    "name": "Rosaline",
    "isFavourite": false,
    "image": "http://dummyimage.com/158x245.png/ff4444/ffffff",
    "groups": []
  },
  {
    "uuid": "919d4e85-6240-40c9-b399-c0ece8b079a0",
    "name": "Kim",
    "isFavourite": true,
    "image": "http://dummyimage.com/202x208.bmp/5fa2dd/ffffff",
    "groups": []
  },
  {
    "uuid": "aaff2c80-76bc-4daa-ae1a-75fc513d2bd9",
    "name": "Bibi",
    "isFavourite": false,
    "image": "http://dummyimage.com/170x136.jpg/5fa2dd/ffffff",
    "groups": []
  },
  {
    "uuid": "82c4513a-2596-4dfe-b7d3-e9252cdc6ba2",
    "name": "Nappy",
    "isFavourite": true,
    "image": "http://dummyimage.com/149x211.jpg/ff4444/ffffff",
    "groups": []
  },
  {
    "uuid": "5e170aac-8889-4912-8d5c-1c9e4adb3670",
    "name": "Bonni",
    "isFavourite": true,
    "image": "http://dummyimage.com/100x212.bmp/ff4444/ffffff",
    "groups": []
  },
  {
    "uuid": "fc8e39d8-c472-4e67-87ef-44df1f941298",
    "name": "Ashley",
    "isFavourite": true,
    "image": "http://dummyimage.com/190x156.bmp/dddddd/000000",
    "groups": []
  },
  {
    "uuid": "7486df04-d9bc-4a54-97f4-515df5736566",
    "name": "Jolene",
    "isFavourite": false,
    "image": "http://dummyimage.com/156x131.jpg/cc0000/ffffff",
    "groups": []
  },
  {
    "uuid": "7cc21501-0f71-42f8-a300-35b964a82ef3",
    "name": "Eilis",
    "isFavourite": true,
    "image": "http://dummyimage.com/163x219.jpg/ff4444/ffffff",
    "groups": []
  },
  {
    "uuid": "9688a730-3ac7-4bec-b199-7ea22d06a14b",
    "name": "Raul",
    "isFavourite": false,
    "image": "http://dummyimage.com/179x116.jpg/dddddd/000000",
    "groups": []
  },
  {
    "uuid": "6b5dd2c4-3811-4d11-863b-cf236ec0f067",
    "name": "Kynthia",
    "isFavourite": true,
    "image": "http://dummyimage.com/119x192.jpg/dddddd/000000",
    "groups": []
  },
  {
    "uuid": "c148a871-6eef-487b-a210-9178cc12ec5d",
    "name": "Halie",
    "isFavourite": true,
    "image": "http://dummyimage.com/181x149.png/dddddd/000000",
    "groups": []
  },
  {
    "uuid": "a720424e-be12-4eb4-ab97-d5b34444e814",
    "name": "Tito",
    "isFavourite": false,
    "image": "http://dummyimage.com/152x154.png/dddddd/000000",
    "groups": []
  },
  {
    "uuid": "ae58a7ed-e6c5-4052-948c-cb8f56d4ba26",
    "name": "Gloriana",
    "isFavourite": false,
    "image": "http://dummyimage.com/220x233.png/dddddd/000000",
    "groups": []
  },
  {
    "uuid": "b3355948-b5b9-4aab-8298-25ae4bdb4c7c",
    "name": "Tildie",
    "isFavourite": true,
    "image": "http://dummyimage.com/117x191.jpg/5fa2dd/ffffff",
    "groups": []
  },
  {
    "uuid": "e438b4dc-88a0-48f8-88fb-ca8beeb65925",
    "name": "Allie",
    "isFavourite": false,
    "image": "http://dummyimage.com/239x231.bmp/cc0000/ffffff",
    "groups": []
  },
  {
    "uuid": "b0a9c2cf-4db1-4c55-ad38-f70eaf24e36f",
    "name": "Violetta",
    "isFavourite": true,
    "image": "http://dummyimage.com/165x134.png/ff4444/ffffff",
    "groups": []
  },
  {
    "uuid": "c23397c2-6ef3-494a-b5ac-e26d5bca3da3",
    "name": "Lewiss",
    "isFavourite": false,
    "image": "http://dummyimage.com/163x170.bmp/dddddd/000000",
    "groups": []
  },
  {
    "uuid": "9c66ba0f-79de-4bf5-8626-c0f5c1fa4864",
    "name": "Hugibert",
    "isFavourite": true,
    "image": "http://dummyimage.com/180x180.bmp/cc0000/ffffff",
    "groups": []
  },
  {
    "uuid": "80b475af-5ddd-474a-9d13-55f1d2778c82",
    "name": "Kailey",
    "isFavourite": false,
    "image": "http://dummyimage.com/169x100.bmp/cc0000/ffffff",
    "groups": []
  },
  {
    "uuid": "591027f5-b213-45a5-9133-210a07b5403a",
    "name": "Florie",
    "isFavourite": true,
    "image": "http://dummyimage.com/224x140.bmp/dddddd/000000",
    "groups": []
  },
  {
    "uuid": "d8ecd37f-c790-4e95-a838-4b4beedf7091",
    "name": "Forbes",
    "isFavourite": false,
    "image": "http://dummyimage.com/164x134.png/5fa2dd/ffffff",
    "groups": []
  },
  {
    "uuid": "6e9a4e11-905d-4a2b-a088-db31afd7a09b",
    "name": "Gertie",
    "isFavourite": false,
    "image": "http://dummyimage.com/249x110.jpg/dddddd/000000",
    "groups": []
  },
  {
    "uuid": "d460d65c-c5a2-4794-bcdd-dddcffa45256",
    "name": "Del",
    "isFavourite": true,
    "image": "http://dummyimage.com/246x169.png/5fa2dd/ffffff",
    "groups": []
  },
  {
    "uuid": "026571cf-d3d6-467b-8891-2e56593061a4",
    "name": "Rodolfo",
    "isFavourite": true,
    "image": "http://dummyimage.com/198x109.jpg/ff4444/ffffff",
    "groups": []
  },
  {
    "uuid": "7e181192-687d-40b2-8182-5f6ddc116d0e",
    "name": "Percival",
    "isFavourite": false,
    "image": "http://dummyimage.com/120x102.jpg/5fa2dd/ffffff",
    "groups": []
  },
  {
    "uuid": "2fa19421-0f01-4818-ace0-17be0107de6a",
    "name": "Ailey",
    "isFavourite": false,
    "image": "http://dummyimage.com/132x122.png/5fa2dd/ffffff",
    "groups": []
  },
  {
    "uuid": "3efe3661-8c75-42e4-bc83-db16fcdfff0a",
    "name": "Zia",
    "isFavourite": false,
    "image": "http://dummyimage.com/145x120.jpg/dddddd/000000",
    "groups": []
  },
  {
    "uuid": "bd32f7ce-bd92-4930-ab12-dcfd98876e6b",
    "name": "Merlina",
    "isFavourite": true,
    "image": "http://dummyimage.com/186x137.png/ff4444/ffffff",
    "groups": []
  },
  {
    "uuid": "6aadd66f-e855-4b28-ad0f-23d05f449e2e",
    "name": "Stephi",
    "isFavourite": false,
    "image": "http://dummyimage.com/124x216.jpg/ff4444/ffffff",
    "groups": []
  },
  {
    "uuid": "f3a800f5-b69e-4d42-8c23-7c3bebf782fe",
    "name": "Blair",
    "isFavourite": true,
    "image": "http://dummyimage.com/238x203.jpg/5fa2dd/ffffff",
    "groups": []
  },
  {
    "uuid": "5ff10193-d676-4f3d-a28c-27a2aea347b0",
    "name": "Wiley",
    "isFavourite": true,
    "image": "http://dummyimage.com/226x210.jpg/dddddd/000000",
    "groups": []
  },
  {
    "uuid": "80c39fd5-68be-44c6-b312-a0e1975eac38",
    "name": "Kelvin",
    "isFavourite": false,
    "image": "http://dummyimage.com/229x246.jpg/dddddd/000000",
    "groups": []
  },
  {
    "uuid": "b8505a1a-10af-4227-8e50-0edade962215",
    "name": "Maia",
    "isFavourite": false,
    "image": "http://dummyimage.com/180x129.jpg/dddddd/000000",
    "groups": []
  },
  {
    "uuid": "687cafa1-636b-4b96-a137-d1cc00e2b404",
    "name": "Alfreda",
    "isFavourite": false,
    "image": "http://dummyimage.com/116x116.bmp/5fa2dd/ffffff",
    "groups": []
  },
  {
    "uuid": "6ec784b3-277c-432b-9ee3-31a492ad7bb8",
    "name": "Akim",
    "isFavourite": false,
    "image": "http://dummyimage.com/241x232.jpg/cc0000/ffffff",
    "groups": []
  },
  {
    "uuid": "17d4ba71-0e92-4184-a241-e40ae520b962",
    "name": "Gray",
    "isFavourite": true,
    "image": "http://dummyimage.com/183x184.bmp/cc0000/ffffff",
    "groups": []
  },
  {
    "uuid": "b39936c9-60cd-4d6e-9dd3-db16cf6cd7c8",
    "name": "Carlo",
    "isFavourite": true,
    "image": "http://dummyimage.com/228x211.bmp/dddddd/000000",
    "groups": []
  },
  {
    "uuid": "d0a46c27-5e21-4b6d-80a1-a8ff17a7e241",
    "name": "Lukas",
    "isFavourite": true,
    "image": "http://dummyimage.com/228x239.jpg/ff4444/ffffff",
    "groups": []
  },
  {
    "uuid": "a74b2bb4-31c7-4948-b294-e1f1e6dd4bb9",
    "name": "Ivory",
    "isFavourite": true,
    "image": "http://dummyimage.com/212x184.png/dddddd/000000",
    "groups": []
  },
  {
    "uuid": "3e47d092-d49c-4b01-906b-c92bc22fbb80",
    "name": "Enrichetta",
    "isFavourite": false,
    "image": "http://dummyimage.com/106x199.png/5fa2dd/ffffff",
    "groups": []
  },
  {
    "uuid": "f07cd03f-aae2-4cee-a01f-1834ca203039",
    "name": "Normand",
    "isFavourite": true,
    "image": "http://dummyimage.com/248x226.png/ff4444/ffffff",
    "groups": []
  },
  {
    "uuid": "8fc6f9e6-9b3a-4148-b7a8-98f402203d2b",
    "name": "Alexine",
    "isFavourite": true,
    "image": "http://dummyimage.com/105x224.bmp/ff4444/ffffff",
    "groups": []
  },
  {
    "uuid": "7c1589a6-868e-464c-8ba9-96822fd7bc5c",
    "name": "Janie",
    "isFavourite": true,
    "image": "http://dummyimage.com/127x232.bmp/5fa2dd/ffffff",
    "groups": []
  },
  {
    "uuid": "bc6a09e9-1d8b-41ba-bca8-d08cada75ac8",
    "name": "Betti",
    "isFavourite": false,
    "image": "http://dummyimage.com/245x101.png/cc0000/ffffff",
    "groups": []
  },
  {
    "uuid": "ae21cc5f-58bf-4945-8a41-23e65b72eb02",
    "name": "Roxine",
    "isFavourite": false,
    "image": "http://dummyimage.com/240x214.bmp/dddddd/000000",
    "groups": []
  },
  {
    "uuid": "3c2f198c-caac-4fc6-a68c-448b1c598590",
    "name": "Angelina",
    "isFavourite": true,
    "image": "http://dummyimage.com/250x184.png/5fa2dd/ffffff",
    "groups": []
  },
  {
    "uuid": "2ba3c845-92be-4610-82ae-0628d984725d",
    "name": "Jerri",
    "isFavourite": true,
    "image": "http://dummyimage.com/177x222.png/ff4444/ffffff",
    "groups": []
  },
  {
    "uuid": "bd700ef1-cab8-4ee4-83bf-d37059e64731",
    "name": "Sibylla",
    "isFavourite": false,
    "image": "http://dummyimage.com/154x215.png/cc0000/ffffff",
    "groups": []
  },
  {
    "uuid": "315557af-118b-422a-b015-ec6acf699087",
    "name": "Tove",
    "isFavourite": false,
    "image": "http://dummyimage.com/137x178.bmp/ff4444/ffffff",
    "groups": []
  },
  {
    "uuid": "17b41717-5a7f-43df-a266-bb1cf7c19412",
    "name": "Stephi",
    "isFavourite": true,
    "image": "http://dummyimage.com/102x224.bmp/dddddd/000000",
    "groups": []
  },
  {
    "uuid": "de84c2b6-9618-411c-beeb-301679ce464f",
    "name": "Rusty",
    "isFavourite": false,
    "image": "http://dummyimage.com/246x117.png/ff4444/ffffff",
    "groups": []
  },
  {
    "uuid": "3beff425-a947-40fd-8724-9c81039ebc1a",
    "name": "Chickie",
    "isFavourite": true,
    "image": "http://dummyimage.com/203x133.bmp/ff4444/ffffff",
    "groups": []
  },
  {
    "uuid": "0876e54c-ed2d-4b43-8f6b-057b023ff919",
    "name": "Cornie",
    "isFavourite": false,
    "image": "http://dummyimage.com/220x182.bmp/ff4444/ffffff",
    "groups": []
  },
  {
    "uuid": "195bc02e-1de2-4f35-8f06-bc1933b139f0",
    "name": "Nickolaus",
    "isFavourite": true,
    "image": "http://dummyimage.com/173x224.bmp/cc0000/ffffff",
    "groups": []
  },
  {
    "uuid": "659a16de-f76e-4581-b41d-52689c58838c",
    "name": "Min",
    "isFavourite": true,
    "image": "http://dummyimage.com/119x139.png/cc0000/ffffff",
    "groups": []
  },
  {
    "uuid": "580a0a59-e602-4b1c-a36d-139b675d9ca9",
    "name": "Jodie",
    "isFavourite": false,
    "image": "http://dummyimage.com/146x188.jpg/5fa2dd/ffffff",
    "groups": []
  },
  {
    "uuid": "3b2cc466-0d0c-4d71-8491-a2813e9e204d",
    "name": "Stevana",
    "isFavourite": false,
    "image": "http://dummyimage.com/132x150.bmp/ff4444/ffffff",
    "groups": []
  },
  {
    "uuid": "97f07901-18f7-4e12-b8d2-7bad6fe38421",
    "name": "Bronnie",
    "isFavourite": true,
    "image": "http://dummyimage.com/149x155.jpg/5fa2dd/ffffff",
    "groups": []
  },
  {
    "uuid": "fbdf32a9-7132-4991-b7ce-c9f46a8a3d68",
    "name": "Garrett",
    "isFavourite": false,
    "image": "http://dummyimage.com/140x130.bmp/dddddd/000000",
    "groups": []
  },
  {
    "uuid": "357838a8-5fe6-4b9e-b279-e7729718b61e",
    "name": "Tess",
    "isFavourite": false,
    "image": "http://dummyimage.com/241x240.png/dddddd/000000",
    "groups": []
  },
  {
    "uuid": "a615e3bd-0eed-4558-903b-e1ebaa9b12a6",
    "name": "Audre",
    "isFavourite": true,
    "image": "http://dummyimage.com/174x167.jpg/dddddd/000000",
    "groups": []
  },
  {
    "uuid": "e5cc12d9-4db8-4b81-bed2-f9f3d1cdabab",
    "name": "Lauren",
    "isFavourite": true,
    "image": "http://dummyimage.com/140x164.png/cc0000/ffffff",
    "groups": []
  },
  {
    "uuid": "2c73503f-b9af-4694-a5b7-09d535a5b098",
    "name": "Sonnnie",
    "isFavourite": false,
    "image": "http://dummyimage.com/174x165.jpg/5fa2dd/ffffff",
    "groups": []
  },
  {
    "uuid": "b8afd7c4-4e86-43e7-abeb-8a9a82d5d155",
    "name": "Sarene",
    "isFavourite": false,
    "image": "http://dummyimage.com/154x134.png/dddddd/000000",
    "groups": []
  },
  {
    "uuid": "0fea6ee7-f3ec-4ed0-b615-8cde6576a458",
    "name": "Perice",
    "isFavourite": false,
    "image": "http://dummyimage.com/158x179.png/cc0000/ffffff",
    "groups": []
  },
  {
    "uuid": "20855bfc-ab7f-4def-ac1b-95cc19b5dc70",
    "name": "Lorant",
    "isFavourite": false,
    "image": "http://dummyimage.com/232x207.bmp/cc0000/ffffff",
    "groups": []
  },
  {
    "uuid": "c9eb4396-c5ed-4fb5-92f5-01f579ff857a",
    "name": "Lawry",
    "isFavourite": true,
    "image": "http://dummyimage.com/161x139.bmp/cc0000/ffffff",
    "groups": []
  },
  {
    "uuid": "2ed2f028-3b5e-43d6-a9ac-87382b4cf970",
    "name": "Matteo",
    "isFavourite": false,
    "image": "http://dummyimage.com/105x245.png/cc0000/ffffff",
    "groups": []
  },
  {
    "uuid": "f9887c5d-b659-498b-9dd4-d429027f546a",
    "name": "Philomena",
    "isFavourite": false,
    "image": "http://dummyimage.com/219x215.png/dddddd/000000",
    "groups": []
  },
  {
    "uuid": "8ef0ce05-b40a-468a-a3c6-a64e6040ee6c",
    "name": "Allsun",
    "isFavourite": true,
    "image": "http://dummyimage.com/104x144.png/cc0000/ffffff",
    "groups": []
  },
  {
    "uuid": "e304719d-9ccc-465d-b76b-2db01b141cfa",
    "name": "Bren",
    "isFavourite": true,
    "image": "http://dummyimage.com/176x220.jpg/5fa2dd/ffffff",
    "groups": []
  },
  {
    "uuid": "64d792f8-1409-434d-91c5-d47d19da8b3b",
    "name": "Giulietta",
    "isFavourite": false,
    "image": "http://dummyimage.com/138x211.png/dddddd/000000",
    "groups": []
  },
  {
    "uuid": "061eb85a-4257-4f87-90b0-eceafe982ec1",
    "name": "Pepito",
    "isFavourite": true,
    "image": "http://dummyimage.com/107x132.png/ff4444/ffffff",
    "groups": []
  },
  {
    "uuid": "e3e6a631-c13e-44c2-8683-3d36c2801174",
    "name": "Meredithe",
    "isFavourite": true,
    "image": "http://dummyimage.com/219x119.png/cc0000/ffffff",
    "groups": []
  },
  {
    "uuid": "7ec31cc5-55cc-4657-9559-b418a580e342",
    "name": "Corny",
    "isFavourite": false,
    "image": "http://dummyimage.com/174x224.jpg/ff4444/ffffff",
    "groups": []
  },
  {
    "uuid": "4d2cce9c-b124-4543-9536-cb7140e5347e",
    "name": "Thatcher",
    "isFavourite": false,
    "image": "http://dummyimage.com/239x104.bmp/ff4444/ffffff",
    "groups": []
  },
  {
    "uuid": "45273dfc-87b5-4874-89d4-ac5c9cb6727a",
    "name": "Georgianna",
    "isFavourite": true,
    "image": "http://dummyimage.com/147x110.jpg/ff4444/ffffff",
    "groups": []
  },
  {
    "uuid": "da6ec3ba-05a9-4e6e-ba3b-7d6ed2540886",
    "name": "Kirsten",
    "isFavourite": false,
    "image": "http://dummyimage.com/207x242.bmp/dddddd/000000",
    "groups": []
  },
  {
    "uuid": "e3dfbd79-71b7-4f79-80aa-3c5e24e979e6",
    "name": "Amitie",
    "isFavourite": true,
    "image": "http://dummyimage.com/133x167.jpg/ff4444/ffffff",
    "groups": []
  },
  {
    "uuid": "07651c1e-9221-4007-99ea-e7dc8d66f6a6",
    "name": "Dyane",
    "isFavourite": false,
    "image": "http://dummyimage.com/133x129.jpg/dddddd/000000",
    "groups": []
  },
  {
    "uuid": "d0540d82-f116-4f6b-9fc5-deb5d3265c48",
    "name": "Ramonda",
    "isFavourite": false,
    "image": "http://dummyimage.com/226x223.bmp/5fa2dd/ffffff",
    "groups": []
  },
  {
    "uuid": "e1fcb267-0bf2-41a1-b383-768d83076f3d",
    "name": "Garnette",
    "isFavourite": false,
    "image": "http://dummyimage.com/223x108.bmp/dddddd/000000",
    "groups": []
  },
  {
    "uuid": "b727ad2a-f359-4b39-9c9a-d105daec5607",
    "name": "Gerda",
    "isFavourite": true,
    "image": "http://dummyimage.com/225x245.png/dddddd/000000",
    "groups": []
  },
  {
    "uuid": "b78747c2-99af-4570-aadb-2904331d1618",
    "name": "Averell",
    "isFavourite": false,
    "image": "http://dummyimage.com/235x105.png/ff4444/ffffff",
    "groups": []
  },
  {
    "uuid": "43808714-07a3-4097-9dd6-f94797567bb8",
    "name": "Florina",
    "isFavourite": true,
    "image": "http://dummyimage.com/179x189.jpg/cc0000/ffffff",
    "groups": []
  },
  {
    "uuid": "ba5d164f-605f-400e-924b-e808048fc00c",
    "name": "Ann",
    "isFavourite": false,
    "image": "http://dummyimage.com/246x179.bmp/dddddd/000000",
    "groups": []
  },
  {
    "uuid": "a4a3f320-fded-419e-a2b2-f9d7021aad96",
    "name": "Robina",
    "isFavourite": false,
    "image": "http://dummyimage.com/105x138.jpg/dddddd/000000",
    "groups": []
  },
  {
    "uuid": "d1206372-8a5f-4bba-b6c9-ce86ffc167e4",
    "name": "Elizabet",
    "isFavourite": false,
    "image": "http://dummyimage.com/239x105.bmp/dddddd/000000",
    "groups": []
  },
  {
    "uuid": "af5c068d-a670-4d9c-9ac2-3e3ebc6570ab",
    "name": "Filippo",
    "isFavourite": true,
    "image": "http://dummyimage.com/158x223.jpg/dddddd/000000",
    "groups": []
  },
  {
    "uuid": "4242bdff-d5ec-4d9f-ac95-e8479411ca69",
    "name": "Sampson",
    "isFavourite": true,
    "image": "http://dummyimage.com/236x173.jpg/5fa2dd/ffffff",
    "groups": []
  },
  {
    "uuid": "367158e6-dbb0-4e66-8acc-ee6475bfd0c5",
    "name": "Devondra",
    "isFavourite": true,
    "image": "http://dummyimage.com/146x143.jpg/ff4444/ffffff",
    "groups": []
  },
  {
    "uuid": "99a18194-55cf-441e-872c-29de8aec40ce",
    "name": "Spense",
    "isFavourite": true,
    "image": "http://dummyimage.com/119x104.png/cc0000/ffffff",
    "groups": []
  },
  {
    "uuid": "5de7a8b3-7567-4485-906b-8bf848fccf60",
    "name": "Gibb",
    "isFavourite": true,
    "image": "http://dummyimage.com/249x120.jpg/5fa2dd/ffffff",
    "groups": []
  },
  {
    "uuid": "b5083f0e-1779-47fa-bb08-452651910744",
    "name": "Leona",
    "isFavourite": true,
    "image": "http://dummyimage.com/239x224.png/dddddd/000000",
    "groups": []
  },
  {
    "uuid": "050f8b57-0e0d-4901-bb71-42a11909be17",
    "name": "Dulsea",
    "isFavourite": true,
    "image": "http://dummyimage.com/102x189.png/5fa2dd/ffffff",
    "groups": []
  },
  {
    "uuid": "53400a3d-6116-45ca-bde5-f78c4849c17d",
    "name": "Arlen",
    "isFavourite": true,
    "image": "http://dummyimage.com/139x164.bmp/5fa2dd/ffffff",
    "groups": []
  },
  {
    "uuid": "a12a7e45-78a7-465a-9f9f-ba1d2ee9da46",
    "name": "Mattias",
    "isFavourite": true,
    "image": "http://dummyimage.com/186x225.jpg/dddddd/000000",
    "groups": []
  },
  {
    "uuid": "5e7ed515-fd0b-4ca6-b506-2f4ca15db398",
    "name": "Lauren",
    "isFavourite": true,
    "image": "http://dummyimage.com/101x241.bmp/5fa2dd/ffffff",
    "groups": []
  },
  {
    "uuid": "76c16607-decc-45a9-8349-278bf233810b",
    "name": "Ileana",
    "isFavourite": true,
    "image": "http://dummyimage.com/137x137.bmp/5fa2dd/ffffff",
    "groups": []
  },
  {
    "uuid": "0b313a42-5203-44c5-b4e0-cdca08d00a5a",
    "name": "Jen",
    "isFavourite": false,
    "image": "http://dummyimage.com/106x124.bmp/ff4444/ffffff",
    "groups": []
  },
  {
    "uuid": "85aadd74-4ec3-46ef-9521-9570596c1c87",
    "name": "Hebert",
    "isFavourite": false,
    "image": "http://dummyimage.com/222x219.bmp/5fa2dd/ffffff",
    "groups": []
  },
  {
    "uuid": "7077faaa-7e3b-4e40-8136-7bc7faf9a5ba",
    "name": "Saundra",
    "isFavourite": true,
    "image": "http://dummyimage.com/209x124.jpg/dddddd/000000",
    "groups": []
  },
  {
    "uuid": "6e6efa82-07ef-4008-a288-55a48260b33e",
    "name": "Letta",
    "isFavourite": true,
    "image": "http://dummyimage.com/245x129.bmp/dddddd/000000",
    "groups": []
  },
  {
    "uuid": "b8a6692e-b36c-4cf2-b361-873b00583b49",
    "name": "Tami",
    "isFavourite": true,
    "image": "http://dummyimage.com/183x216.png/ff4444/ffffff",
    "groups": []
  },
  {
    "uuid": "8c76432e-8dec-4c5b-a871-c83276cbe7d3",
    "name": "Alfredo",
    "isFavourite": true,
    "image": "http://dummyimage.com/226x249.png/ff4444/ffffff",
    "groups": []
  },
  {
    "uuid": "c9bb8fc6-655d-45ec-981e-004795dec087",
    "name": "Rebbecca",
    "isFavourite": false,
    "image": "http://dummyimage.com/114x213.bmp/5fa2dd/ffffff",
    "groups": []
  },
  {
    "uuid": "9407a592-65d6-4dbe-8f42-30885157be7b",
    "name": "Adriaens",
    "isFavourite": false,
    "image": "http://dummyimage.com/136x228.bmp/cc0000/ffffff",
    "groups": []
  },
  {
    "uuid": "e937b60b-5648-4bcd-84a6-b5e375c2ee6c",
    "name": "Jessey",
    "isFavourite": false,
    "image": "http://dummyimage.com/205x117.jpg/dddddd/000000",
    "groups": []
  },
  {
    "uuid": "a4986185-cc40-480a-8c7f-3e93a5681209",
    "name": "Mae",
    "isFavourite": false,
    "image": "http://dummyimage.com/222x194.png/dddddd/000000",
    "groups": []
  },
  {
    "uuid": "4178632c-3700-4495-ad8e-779906c8ae49",
    "name": "Lenette",
    "isFavourite": false,
    "image": "http://dummyimage.com/182x218.png/dddddd/000000",
    "groups": []
  },
  {
    "uuid": "b9dc8ab5-7ce6-4a79-b3df-e1e4ebd91a3e",
    "name": "Gilda",
    "isFavourite": false,
    "image": "http://dummyimage.com/200x168.jpg/5fa2dd/ffffff",
    "groups": []
  },
  {
    "uuid": "7a1934a8-1311-4ad9-9c24-cfccb2adb337",
    "name": "Gilda",
    "isFavourite": false,
    "image": "http://dummyimage.com/238x126.jpg/5fa2dd/ffffff",
    "groups": []
  },
  {
    "uuid": "6fb7ddca-bd5a-4510-a02b-e6a02c0abc20",
    "name": "Brion",
    "isFavourite": false,
    "image": "http://dummyimage.com/232x206.bmp/ff4444/ffffff",
    "groups": []
  },
  {
    "uuid": "8c03bf50-bb6e-48cf-beb8-c16b94b36bb7",
    "name": "Randa",
    "isFavourite": false,
    "image": "http://dummyimage.com/219x135.png/dddddd/000000",
    "groups": []
  },
  {
    "uuid": "e8fb9746-bf20-4aa6-8044-d6db8263d924",
    "name": "Sib",
    "isFavourite": false,
    "image": "http://dummyimage.com/134x180.bmp/ff4444/ffffff",
    "groups": []
  },
  {
    "uuid": "37045efd-5bd3-4ba8-8241-40aa9e259db1",
    "name": "Anabel",
    "isFavourite": true,
    "image": "http://dummyimage.com/238x168.png/cc0000/ffffff",
    "groups": []
  },
  {
    "uuid": "eb381fbe-5da9-469c-9776-bbbc1600ba04",
    "name": "Marne",
    "isFavourite": true,
    "image": "http://dummyimage.com/120x135.png/cc0000/ffffff",
    "groups": []
  },
  {
    "uuid": "a0f94e68-bc12-4907-88f8-aa9609d3ff03",
    "name": "Gerda",
    "isFavourite": true,
    "image": "http://dummyimage.com/218x104.jpg/cc0000/ffffff",
    "groups": []
  },
  {
    "uuid": "708721e4-cc4b-45db-b412-4c4d7346df82",
    "name": "Joelynn",
    "isFavourite": true,
    "image": "http://dummyimage.com/156x239.png/ff4444/ffffff",
    "groups": []
  },
  {
    "uuid": "8a3c7930-9cae-4c48-b0a5-deab7542994c",
    "name": "Todd",
    "isFavourite": false,
    "image": "http://dummyimage.com/127x115.jpg/5fa2dd/ffffff",
    "groups": []
  },
  {
    "uuid": "45e77f2e-6547-4328-bbba-082753b86259",
    "name": "Starlin",
    "isFavourite": true,
    "image": "http://dummyimage.com/220x190.jpg/ff4444/ffffff",
    "groups": []
  },
  {
    "uuid": "accf40c1-4114-4895-923f-34fbf43d669b",
    "name": "Noe",
    "isFavourite": false,
    "image": "http://dummyimage.com/154x178.jpg/5fa2dd/ffffff",
    "groups": []
  },
  {
    "uuid": "2b96f165-596b-422c-9115-4c25051a553e",
    "name": "Hadleigh",
    "isFavourite": true,
    "image": "http://dummyimage.com/201x120.png/dddddd/000000",
    "groups": []
  },
  {
    "uuid": "092c2060-daec-4f93-8095-6572788c1237",
    "name": "Ford",
    "isFavourite": false,
    "image": "http://dummyimage.com/238x139.png/cc0000/ffffff",
    "groups": []
  },
  {
    "uuid": "d3c3adc7-9cd3-4bf2-9ad0-c4b70a3208a0",
    "name": "Sunshine",
    "isFavourite": false,
    "image": "http://dummyimage.com/139x153.png/cc0000/ffffff",
    "groups": []
  },
  {
    "uuid": "353d3f37-3f9d-4abd-81c6-9556252a1715",
    "name": "Guinna",
    "isFavourite": true,
    "image": "http://dummyimage.com/141x194.bmp/ff4444/ffffff",
    "groups": []
  },
  {
    "uuid": "5406ac0a-eeb9-4802-8f7e-dfbd32416ba8",
    "name": "Laryssa",
    "isFavourite": false,
    "image": "http://dummyimage.com/212x160.png/dddddd/000000",
    "groups": []
  },
  {
    "uuid": "cba5fc59-261c-44cb-abd3-2f630c7c1916",
    "name": "Loree",
    "isFavourite": true,
    "image": "http://dummyimage.com/142x217.jpg/ff4444/ffffff",
    "groups": []
  },
  {
    "uuid": "bc406f18-a9da-49f5-a4f3-fdf61761f70c",
    "name": "Danyelle",
    "isFavourite": false,
    "image": "http://dummyimage.com/160x142.png/ff4444/ffffff",
    "groups": []
  },
  {
    "uuid": "9c6a834c-a423-40c8-b4c2-5a93d0e53e9e",
    "name": "Emmit",
    "isFavourite": false,
    "image": "http://dummyimage.com/250x233.png/cc0000/ffffff",
    "groups": []
  },
  {
    "uuid": "23c90dca-f3e2-43e5-aaad-796e3668e456",
    "name": "Arlin",
    "isFavourite": true,
    "image": "http://dummyimage.com/211x172.jpg/5fa2dd/ffffff",
    "groups": []
  },
  {
    "uuid": "6ff776d1-7bc6-41ec-a454-fadd929ecd89",
    "name": "Harlene",
    "isFavourite": true,
    "image": "http://dummyimage.com/110x168.png/cc0000/ffffff",
    "groups": []
  },
  {
    "uuid": "e4fb0ae2-ef60-4d7e-b9fa-e6b725f8b0f1",
    "name": "Lindy",
    "isFavourite": false,
    "image": "http://dummyimage.com/241x151.jpg/ff4444/ffffff",
    "groups": []
  },
  {
    "uuid": "95cea6f5-3fa2-4c73-9e3d-32f2009790c1",
    "name": "Christopher",
    "isFavourite": true,
    "image": "http://dummyimage.com/187x115.bmp/dddddd/000000",
    "groups": []
  },
  {
    "uuid": "f73baf89-5b3a-4997-842e-b25e6692ab89",
    "name": "Pia",
    "isFavourite": true,
    "image": "http://dummyimage.com/211x127.png/cc0000/ffffff",
    "groups": []
  },
  {
    "uuid": "24754570-3b25-45b2-a516-a8e766aec110",
    "name": "Iain",
    "isFavourite": true,
    "image": "http://dummyimage.com/215x205.bmp/dddddd/000000",
    "groups": []
  },
  {
    "uuid": "8ce470fb-9f20-48ac-bb79-30e9d97d5ebe",
    "name": "Carmelina",
    "isFavourite": false,
    "image": "http://dummyimage.com/187x217.png/cc0000/ffffff",
    "groups": []
  },
  {
    "uuid": "23f04255-7ba9-4d87-a8fb-1258f6ab90b8",
    "name": "Jory",
    "isFavourite": false,
    "image": "http://dummyimage.com/145x110.bmp/cc0000/ffffff",
    "groups": []
  },
  {
    "uuid": "a0826e0b-6840-4edc-95a0-4c4353697494",
    "name": "Guillermo",
    "isFavourite": false,
    "image": "http://dummyimage.com/139x229.png/ff4444/ffffff",
    "groups": []
  },
  {
    "uuid": "abb9a902-72d2-444d-93e5-088ba2bedcc5",
    "name": "Angelique",
    "isFavourite": true,
    "image": "http://dummyimage.com/171x116.bmp/ff4444/ffffff",
    "groups": []
  },
  {
    "uuid": "448968c8-4f56-417d-8a14-e82855aabc1f",
    "name": "Annalise",
    "isFavourite": false,
    "image": "http://dummyimage.com/102x181.bmp/cc0000/ffffff",
    "groups": []
  },
  {
    "uuid": "f538eeb6-1040-4780-9246-27283de1b145",
    "name": "Baily",
    "isFavourite": true,
    "image": "http://dummyimage.com/168x115.jpg/5fa2dd/ffffff",
    "groups": []
  },
  {
    "uuid": "9ebc8c1e-dc06-4a0d-8385-2aaca1742575",
    "name": "Rockwell",
    "isFavourite": false,
    "image": "http://dummyimage.com/190x181.png/dddddd/000000",
    "groups": []
  },
  {
    "uuid": "b6421dd3-d8df-4329-a089-44897f4fc6c3",
    "name": "Nada",
    "isFavourite": true,
    "image": "http://dummyimage.com/124x129.png/cc0000/ffffff",
    "groups": []
  },
  {
    "uuid": "dc70966d-9442-446d-bbd2-544be0c92dde",
    "name": "Dael",
    "isFavourite": true,
    "image": "http://dummyimage.com/100x243.bmp/cc0000/ffffff",
    "groups": []
  },
  {
    "uuid": "90085791-3a56-4ba6-9322-30b284399f61",
    "name": "Susy",
    "isFavourite": false,
    "image": "http://dummyimage.com/121x136.bmp/5fa2dd/ffffff",
    "groups": []
  },
  {
    "uuid": "7a36ffff-79a4-4c78-bc84-339328fed101",
    "name": "Marlyn",
    "isFavourite": true,
    "image": "http://dummyimage.com/123x155.jpg/cc0000/ffffff",
    "groups": []
  },
  {
    "uuid": "b2ba3601-37cc-4168-9971-82c190fdaf14",
    "name": "Kippar",
    "isFavourite": true,
    "image": "http://dummyimage.com/249x217.jpg/ff4444/ffffff",
    "groups": []
  },
  {
    "uuid": "0e353d54-5298-4d1d-a80d-dda3cc04de31",
    "name": "Marshal",
    "isFavourite": false,
    "image": "http://dummyimage.com/216x206.bmp/dddddd/000000",
    "groups": []
  },
  {
    "uuid": "4306173f-be19-463a-8962-672bc75ff2f1",
    "name": "Aldo",
    "isFavourite": false,
    "image": "http://dummyimage.com/175x221.jpg/cc0000/ffffff",
    "groups": []
  },
  {
    "uuid": "5581d1be-bee0-4ee6-9993-bd4a345ef074",
    "name": "Linus",
    "isFavourite": true,
    "image": "http://dummyimage.com/108x196.jpg/cc0000/ffffff",
    "groups": []
  },
  {
    "uuid": "7ec500e5-ca55-4f6e-b363-3365149a6e24",
    "name": "Demetra",
    "isFavourite": false,
    "image": "http://dummyimage.com/142x164.bmp/cc0000/ffffff",
    "groups": []
  },
  {
    "uuid": "9faa2284-1e6a-46c9-bf35-0c58bb46c286",
    "name": "Loren",
    "isFavourite": false,
    "image": "http://dummyimage.com/197x249.bmp/5fa2dd/ffffff",
    "groups": []
  },
  {
    "uuid": "302cf3af-db2b-4f60-8a2d-003e65c943ed",
    "name": "Josie",
    "isFavourite": true,
    "image": "http://dummyimage.com/217x159.bmp/5fa2dd/ffffff",
    "groups": []
  },
  {
    "uuid": "b2288d76-be90-4228-8c1b-e121e1651441",
    "name": "Gianni",
    "isFavourite": true,
    "image": "http://dummyimage.com/208x115.jpg/dddddd/000000",
    "groups": []
  },
  {
    "uuid": "172f35bb-e6b4-4cdc-977d-cf41e8488551",
    "name": "Crissy",
    "isFavourite": true,
    "image": "http://dummyimage.com/126x185.bmp/ff4444/ffffff",
    "groups": []
  },
  {
    "uuid": "a514a5ee-edfd-4f4c-9c2c-9aa6528e7981",
    "name": "Remus",
    "isFavourite": true,
    "image": "http://dummyimage.com/193x185.png/dddddd/000000",
    "groups": []
  },
  {
    "uuid": "e1acbe5f-e392-4d11-8909-494204475031",
    "name": "Waylon",
    "isFavourite": true,
    "image": "http://dummyimage.com/121x120.bmp/cc0000/ffffff",
    "groups": []
  },
  {
    "uuid": "5891e521-4800-49b4-9947-0679bc92271a",
    "name": "Stanford",
    "isFavourite": false,
    "image": "http://dummyimage.com/179x207.jpg/dddddd/000000",
    "groups": []
  },
  {
    "uuid": "6c9e5d3b-bdff-4abf-a472-8c485102b3c9",
    "name": "Prentice",
    "isFavourite": true,
    "image": "http://dummyimage.com/134x190.png/cc0000/ffffff",
    "groups": []
  },
  {
    "uuid": "cfa420d6-5697-419e-96a9-8a8702d774f0",
    "name": "Edithe",
    "isFavourite": true,
    "image": "http://dummyimage.com/214x161.png/5fa2dd/ffffff",
    "groups": []
  },
  {
    "uuid": "1c900801-55c5-49ff-a994-18f8f5de3d3f",
    "name": "Lindi",
    "isFavourite": false,
    "image": "http://dummyimage.com/113x104.jpg/ff4444/ffffff",
    "groups": []
  },
  {
    "uuid": "3e7ecb9a-8e61-4152-8f44-bfcff758edf0",
    "name": "Eolande",
    "isFavourite": true,
    "image": "http://dummyimage.com/126x103.bmp/5fa2dd/ffffff",
    "groups": []
  },
  {
    "uuid": "bca8a5fb-4d4a-4d46-9eb2-9e8dabb88822",
    "name": "Clayson",
    "isFavourite": true,
    "image": "http://dummyimage.com/139x183.jpg/5fa2dd/ffffff",
    "groups": []
  },
  {
    "uuid": "e02eea73-e23a-4dac-a6e6-2150fce8618f",
    "name": "Sibylle",
    "isFavourite": false,
    "image": "http://dummyimage.com/193x185.jpg/ff4444/ffffff",
    "groups": []
  },
  {
    "uuid": "cdc12732-0d9c-45f1-a4c9-8e5d2480fc82",
    "name": "Tull",
    "isFavourite": false,
    "image": "http://dummyimage.com/202x215.jpg/dddddd/000000",
    "groups": []
  },
  {
    "uuid": "c6494780-9e51-482b-a605-c50652c52c23",
    "name": "Andi",
    "isFavourite": false,
    "image": "http://dummyimage.com/117x243.jpg/5fa2dd/ffffff",
    "groups": []
  },
  {
    "uuid": "eb4533e3-fc2b-423b-afc7-cfb751ba7979",
    "name": "Kris",
    "isFavourite": true,
    "image": "http://dummyimage.com/122x186.bmp/5fa2dd/ffffff",
    "groups": []
  },
  {
    "uuid": "fd626c93-8032-4123-984d-65480a64758e",
    "name": "Farris",
    "isFavourite": false,
    "image": "http://dummyimage.com/220x107.png/cc0000/ffffff",
    "groups": []
  },
  {
    "uuid": "8f2fdd22-2e72-4c67-aa2a-a3d270637dce",
    "name": "Quintilla",
    "isFavourite": false,
    "image": "http://dummyimage.com/114x190.png/ff4444/ffffff",
    "groups": []
  },
  {
    "uuid": "f775e828-dd79-4d23-b658-21279da32829",
    "name": "Marlie",
    "isFavourite": true,
    "image": "http://dummyimage.com/101x142.jpg/ff4444/ffffff",
    "groups": []
  },
  {
    "uuid": "7d3e1701-f443-4e72-a9c1-a30e03dada8d",
    "name": "Zsazsa",
    "isFavourite": true,
    "image": "http://dummyimage.com/188x211.jpg/dddddd/000000",
    "groups": []
  },
  {
    "uuid": "c7340eb0-9f32-48d3-a7ef-8c5950fb9777",
    "name": "Mace",
    "isFavourite": true,
    "image": "http://dummyimage.com/202x190.png/dddddd/000000",
    "groups": []
  },
  {
    "uuid": "46de6b88-d043-4c45-bfb2-8225994db7c7",
    "name": "Hestia",
    "isFavourite": true,
    "image": "http://dummyimage.com/207x159.png/cc0000/ffffff",
    "groups": []
  },
  {
    "uuid": "e9d934e5-9fbb-4a4b-b7fa-c0c7ef7aace6",
    "name": "Berky",
    "isFavourite": true,
    "image": "http://dummyimage.com/240x218.png/cc0000/ffffff",
    "groups": []
  },
  {
    "uuid": "e48b2bd5-73b2-4999-adca-94693c0a7910",
    "name": "Claire",
    "isFavourite": true,
    "image": "http://dummyimage.com/131x190.png/5fa2dd/ffffff",
    "groups": []
  },
  {
    "uuid": "7b4d8740-3078-4a73-af73-5aada618e001",
    "name": "Cammy",
    "isFavourite": true,
    "image": "http://dummyimage.com/219x138.bmp/dddddd/000000",
    "groups": []
  },
  {
    "uuid": "39e50d28-fc36-4976-a15b-5cde77a63f6e",
    "name": "Laryssa",
    "isFavourite": false,
    "image": "http://dummyimage.com/101x125.jpg/ff4444/ffffff",
    "groups": []
  },
  {
    "uuid": "1491f99e-a3c1-4949-a889-f0106e26d861",
    "name": "Chadd",
    "isFavourite": true,
    "image": "http://dummyimage.com/148x193.png/cc0000/ffffff",
    "groups": []
  },
  {
    "uuid": "7d36d29e-b017-490b-905e-4a815ff7a767",
    "name": "Philippa",
    "isFavourite": false,
    "image": "http://dummyimage.com/172x162.png/ff4444/ffffff",
    "groups": []
  },
  {
    "uuid": "0c46e6eb-4300-42e6-8ee0-14540366769f",
    "name": "Abbey",
    "isFavourite": true,
    "image": "http://dummyimage.com/226x189.jpg/dddddd/000000",
    "groups": []
  },
  {
    "uuid": "cba9526b-1848-4ca0-96b4-0ef255810a19",
    "name": "Gustave",
    "isFavourite": false,
    "image": "http://dummyimage.com/202x135.png/dddddd/000000",
    "groups": []
  },
  {
    "uuid": "0aad6f43-e87b-4f30-948f-6cd4b7f244e0",
    "name": "Marika",
    "isFavourite": false,
    "image": "http://dummyimage.com/120x166.png/ff4444/ffffff",
    "groups": []
  },
  {
    "uuid": "3eb60955-da61-4f87-821d-bd0dd89a64e4",
    "name": "Bent",
    "isFavourite": true,
    "image": "http://dummyimage.com/250x141.png/ff4444/ffffff",
    "groups": []
  },
  {
    "uuid": "8ac01a1d-9404-4604-a2a7-5a951247d9c0",
    "name": "Davin",
    "isFavourite": false,
    "image": "http://dummyimage.com/122x207.bmp/ff4444/ffffff",
    "groups": []
  },
  {
    "uuid": "247f723c-b1dd-4d41-9825-49d0bec12b89",
    "name": "Renault",
    "isFavourite": false,
    "image": "http://dummyimage.com/190x113.bmp/dddddd/000000",
    "groups": []
  },
  {
    "uuid": "5905a68b-cbc5-4bf8-aead-dd579520769a",
    "name": "Reggis",
    "isFavourite": false,
    "image": "http://dummyimage.com/141x248.bmp/dddddd/000000",
    "groups": []
  },
  {
    "uuid": "554f46c8-87c1-44d9-944a-e846280ab462",
    "name": "Ginnie",
    "isFavourite": false,
    "image": "http://dummyimage.com/212x236.bmp/cc0000/ffffff",
    "groups": []
  },
  {
    "uuid": "f520febc-415f-4c27-8ea1-42bbdf6fda65",
    "name": "Matilde",
    "isFavourite": false,
    "image": "http://dummyimage.com/218x134.jpg/5fa2dd/ffffff",
    "groups": []
  },
  {
    "uuid": "79074142-930f-42fb-adf8-497ee896f592",
    "name": "Berti",
    "isFavourite": true,
    "image": "http://dummyimage.com/163x211.jpg/ff4444/ffffff",
    "groups": []
  },
  {
    "uuid": "da02eec9-7d0d-4212-bb46-1ff5111df557",
    "name": "Marysa",
    "isFavourite": true,
    "image": "http://dummyimage.com/108x158.jpg/dddddd/000000",
    "groups": []
  },
  {
    "uuid": "25b1c0f9-0b3e-4088-ba35-77a9b42e104a",
    "name": "Darcey",
    "isFavourite": false,
    "image": "http://dummyimage.com/229x135.jpg/dddddd/000000",
    "groups": []
  },
  {
    "uuid": "db19530f-89d9-423c-967c-2932a38a3899",
    "name": "Cathy",
    "isFavourite": true,
    "image": "http://dummyimage.com/218x134.jpg/cc0000/ffffff",
    "groups": []
  },
  {
    "uuid": "c1b27cec-00f2-4e6d-890f-899b30c06f7a",
    "name": "Hollyanne",
    "isFavourite": true,
    "image": "http://dummyimage.com/214x124.bmp/5fa2dd/ffffff",
    "groups": []
  },
  {
    "uuid": "d271f709-148f-4711-b319-f7a680515caa",
    "name": "Merrili",
    "isFavourite": false,
    "image": "http://dummyimage.com/142x181.png/5fa2dd/ffffff",
    "groups": []
  },
  {
    "uuid": "0b099910-db33-47fb-a2e5-d79359105f12",
    "name": "Eward",
    "isFavourite": false,
    "image": "http://dummyimage.com/186x152.bmp/ff4444/ffffff",
    "groups": []
  },
  {
    "uuid": "e58df31b-a0b6-45cd-85e6-34cfb2bfd62f",
    "name": "Darcie",
    "isFavourite": true,
    "image": "http://dummyimage.com/155x178.jpg/dddddd/000000",
    "groups": []
  },
  {
    "uuid": "3008248b-3745-4677-87ce-92260e1cfbfe",
    "name": "Baron",
    "isFavourite": false,
    "image": "http://dummyimage.com/241x113.jpg/ff4444/ffffff",
    "groups": []
  },
  {
    "uuid": "c38f309a-e01a-4a5b-a62d-8427bc15cdc8",
    "name": "Hiram",
    "isFavourite": true,
    "image": "http://dummyimage.com/221x132.png/dddddd/000000",
    "groups": []
  },
  {
    "uuid": "618a69e5-8b0e-4ee1-a29b-0d843d129546",
    "name": "Margi",
    "isFavourite": false,
    "image": "http://dummyimage.com/117x100.bmp/dddddd/000000",
    "groups": []
  },
  {
    "uuid": "3b6eb71a-887a-4d8d-bd94-bb7527a2e2d6",
    "name": "Davidson",
    "isFavourite": false,
    "image": "http://dummyimage.com/179x114.bmp/ff4444/ffffff",
    "groups": []
  },
  {
    "uuid": "b9809e20-a603-4896-813a-3c9861e50e8f",
    "name": "Tamarra",
    "isFavourite": true,
    "image": "http://dummyimage.com/143x227.bmp/ff4444/ffffff",
    "groups": []
  },
  {
    "uuid": "deb57ba5-8cb8-4c2a-bd13-5dbf0ccb0e95",
    "name": "Tisha",
    "isFavourite": true,
    "image": "http://dummyimage.com/174x199.jpg/ff4444/ffffff",
    "groups": []
  },
  {
    "uuid": "f9bf9483-eb5b-4026-a9bf-ce1d30689b4e",
    "name": "Spence",
    "isFavourite": true,
    "image": "http://dummyimage.com/231x139.bmp/ff4444/ffffff",
    "groups": []
  },
  {
    "uuid": "de5707a5-a6d2-4a6c-ada1-39ba8b1fda08",
    "name": "Raye",
    "isFavourite": true,
    "image": "http://dummyimage.com/202x119.bmp/5fa2dd/ffffff",
    "groups": []
  },
  {
    "uuid": "f70b5568-d7bc-4ae7-9afb-5d5605feddcf",
    "name": "Farr",
    "isFavourite": false,
    "image": "http://dummyimage.com/156x223.png/ff4444/ffffff",
    "groups": []
  },
  {
    "uuid": "0205d591-1cc0-4147-b0ce-10d80047e77c",
    "name": "Woodman",
    "isFavourite": true,
    "image": "http://dummyimage.com/127x167.png/dddddd/000000",
    "groups": []
  },
  {
    "uuid": "5ec66905-81e1-4efd-aa9e-2f17c1cf1a29",
    "name": "Sallee",
    "isFavourite": false,
    "image": "http://dummyimage.com/206x149.jpg/5fa2dd/ffffff",
    "groups": []
  },
  {
    "uuid": "f6a6ff0a-2f4c-406e-8863-0052f8983cd5",
    "name": "Claudetta",
    "isFavourite": false,
    "image": "http://dummyimage.com/151x249.bmp/ff4444/ffffff",
    "groups": []
  },
  {
    "uuid": "e4375e73-b326-4163-99f7-7632336082ea",
    "name": "Randell",
    "isFavourite": true,
    "image": "http://dummyimage.com/222x170.png/5fa2dd/ffffff",
    "groups": []
  },
  {
    "uuid": "8fca3fde-7905-4619-b56a-89b7a25ee039",
    "name": "Rhodie",
    "isFavourite": true,
    "image": "http://dummyimage.com/238x108.jpg/dddddd/000000",
    "groups": []
  },
  {
    "uuid": "8c6daa30-80fc-4bb3-b16b-f83aa430f5f2",
    "name": "Panchito",
    "isFavourite": true,
    "image": "http://dummyimage.com/162x225.png/ff4444/ffffff",
    "groups": []
  },
  {
    "uuid": "161841ca-65a6-41c1-ad4b-e74797803d1f",
    "name": "Celestyn",
    "isFavourite": true,
    "image": "http://dummyimage.com/104x203.bmp/ff4444/ffffff",
    "groups": []
  },
  {
    "uuid": "6c98f8ec-7ec9-4fb7-bd21-8bfefc98a238",
    "name": "Miguelita",
    "isFavourite": true,
    "image": "http://dummyimage.com/224x151.jpg/ff4444/ffffff",
    "groups": []
  },
  {
    "uuid": "f1c61884-5039-4218-83a6-24d3db0d3632",
    "name": "Imogen",
    "isFavourite": false,
    "image": "http://dummyimage.com/191x224.bmp/ff4444/ffffff",
    "groups": []
  },
  {
    "uuid": "e2cfd3dc-1b49-4799-a359-ded272958b87",
    "name": "Amber",
    "isFavourite": true,
    "image": "http://dummyimage.com/184x238.png/5fa2dd/ffffff",
    "groups": []
  },
  {
    "uuid": "ab175aa5-642b-4552-9232-87613e3e1c10",
    "name": "Aleda",
    "isFavourite": true,
    "image": "http://dummyimage.com/198x198.jpg/cc0000/ffffff",
    "groups": []
  },
  {
    "uuid": "3fa75a62-8c3f-4e65-aaf6-a153b00b122e",
    "name": "Persis",
    "isFavourite": false,
    "image": "http://dummyimage.com/124x195.jpg/dddddd/000000",
    "groups": []
  },
  {
    "uuid": "03840ec4-7ea3-486e-ae97-253d8601a4c6",
    "name": "Alida",
    "isFavourite": true,
    "image": "http://dummyimage.com/185x144.jpg/ff4444/ffffff",
    "groups": []
  },
  {
    "uuid": "deea91f6-a46f-44f0-bc0a-1bf37191bce8",
    "name": "Keefe",
    "isFavourite": true,
    "image": "http://dummyimage.com/193x131.jpg/5fa2dd/ffffff",
    "groups": []
  },
  {
    "uuid": "3fb7e053-9e5c-4126-9d31-4131628b5dc5",
    "name": "Britni",
    "isFavourite": true,
    "image": "http://dummyimage.com/189x241.png/5fa2dd/ffffff",
    "groups": []
  },
  {
    "uuid": "c83b05e4-552a-4c44-b1d5-2497c2583530",
    "name": "Alana",
    "isFavourite": true,
    "image": "http://dummyimage.com/195x182.jpg/ff4444/ffffff",
    "groups": []
  },
  {
    "uuid": "70ea763d-a2e9-4ea6-971a-14490d23fffe",
    "name": "Loise",
    "isFavourite": true,
    "image": "http://dummyimage.com/196x102.png/cc0000/ffffff",
    "groups": []
  },
  {
    "uuid": "7d2ae927-a7a6-4bd2-be76-4793b225e8b5",
    "name": "Amalee",
    "isFavourite": true,
    "image": "http://dummyimage.com/192x221.png/cc0000/ffffff",
    "groups": []
  },
  {
    "uuid": "af57806d-5edf-44a4-b6c7-1692dfebc8ab",
    "name": "Jeanelle",
    "isFavourite": false,
    "image": "http://dummyimage.com/117x105.jpg/cc0000/ffffff",
    "groups": []
  },
  {
    "uuid": "1a55ddee-6dce-46e8-be8e-54627e1165d1",
    "name": "Raye",
    "isFavourite": true,
    "image": "http://dummyimage.com/188x101.png/dddddd/000000",
    "groups": []
  },
  {
    "uuid": "529290a5-a374-48ac-96e8-ddaec7c20238",
    "name": "Kahaleel",
    "isFavourite": false,
    "image": "http://dummyimage.com/191x130.bmp/dddddd/000000",
    "groups": []
  },
  {
    "uuid": "468def98-1dba-4681-8a6e-f38479243f22",
    "name": "Biddy",
    "isFavourite": true,
    "image": "http://dummyimage.com/223x134.jpg/ff4444/ffffff",
    "groups": []
  },
  {
    "uuid": "a6af4bfc-9ec5-4e84-8e01-2e13a273e72d",
    "name": "Layton",
    "isFavourite": true,
    "image": "http://dummyimage.com/246x197.jpg/cc0000/ffffff",
    "groups": []
  },
  {
    "uuid": "dc0d43c9-32da-4b26-bc77-7aadc9b69969",
    "name": "Albertine",
    "isFavourite": false,
    "image": "http://dummyimage.com/221x197.png/5fa2dd/ffffff",
    "groups": []
  },
  {
    "uuid": "6529dc46-835f-408f-8604-5020055e309b",
    "name": "Tabitha",
    "isFavourite": false,
    "image": "http://dummyimage.com/245x227.bmp/5fa2dd/ffffff",
    "groups": []
  },
  {
    "uuid": "9493d13f-07c8-412b-8ddd-399d88cddd58",
    "name": "Viviana",
    "isFavourite": true,
    "image": "http://dummyimage.com/111x154.jpg/5fa2dd/ffffff",
    "groups": []
  },
  {
    "uuid": "71af977e-a5c3-4842-b875-78eb08cf147e",
    "name": "Eustacia",
    "isFavourite": false,
    "image": "http://dummyimage.com/123x186.jpg/dddddd/000000",
    "groups": []
  },
  {
    "uuid": "b7d2d80c-5336-45e7-8123-394257d58329",
    "name": "Orbadiah",
    "isFavourite": true,
    "image": "http://dummyimage.com/250x158.bmp/ff4444/ffffff",
    "groups": []
  },
  {
    "uuid": "c5e97ed7-bd90-4111-b56a-ca645b705b50",
    "name": "Brier",
    "isFavourite": true,
    "image": "http://dummyimage.com/120x177.png/ff4444/ffffff",
    "groups": []
  },
  {
    "uuid": "6544a92e-c9b3-4286-9070-03dcb23ae851",
    "name": "Sosanna",
    "isFavourite": true,
    "image": "http://dummyimage.com/209x124.png/cc0000/ffffff",
    "groups": []
  },
  {
    "uuid": "d876fdc0-3399-4b86-aa4e-67f52e538fd3",
    "name": "Keefer",
    "isFavourite": true,
    "image": "http://dummyimage.com/138x200.bmp/cc0000/ffffff",
    "groups": []
  },
  {
    "uuid": "b9cf283c-c96b-43ad-bef2-e2d9a6ee0713",
    "name": "Ogdon",
    "isFavourite": false,
    "image": "http://dummyimage.com/187x174.png/dddddd/000000",
    "groups": []
  },
  {
    "uuid": "82d41599-c3b4-4bc1-85c0-ca8bf7bb89be",
    "name": "Vitoria",
    "isFavourite": true,
    "image": "http://dummyimage.com/157x143.png/5fa2dd/ffffff",
    "groups": []
  },
  {
    "uuid": "29d92851-ad90-4716-a0b7-183e3ff6dbd0",
    "name": "Ethyl",
    "isFavourite": false,
    "image": "http://dummyimage.com/135x197.jpg/dddddd/000000",
    "groups": []
  },
  {
    "uuid": "9d4e6fc1-29e8-41c7-827c-779e147cf7ec",
    "name": "Fraze",
    "isFavourite": false,
    "image": "http://dummyimage.com/117x221.jpg/ff4444/ffffff",
    "groups": []
  },
  {
    "uuid": "2801a958-c42e-46d9-96a7-424a07399006",
    "name": "Delilah",
    "isFavourite": true,
    "image": "http://dummyimage.com/155x240.bmp/cc0000/ffffff",
    "groups": []
  },
  {
    "uuid": "605b0d6a-07e0-494c-82c8-76a11e2ce9b8",
    "name": "Leola",
    "isFavourite": true,
    "image": "http://dummyimage.com/242x234.png/dddddd/000000",
    "groups": []
  },
  {
    "uuid": "50360f8b-d270-4129-898b-4a5e8b67057a",
    "name": "Perl",
    "isFavourite": true,
    "image": "http://dummyimage.com/244x193.png/cc0000/ffffff",
    "groups": []
  },
  {
    "uuid": "731b1de1-c741-409b-b0b9-af809bb51094",
    "name": "Otis",
    "isFavourite": false,
    "image": "http://dummyimage.com/148x231.png/5fa2dd/ffffff",
    "groups": []
  },
  {
    "uuid": "3f09dc5f-72c4-4302-881f-e051c59c1570",
    "name": "Art",
    "isFavourite": false,
    "image": "http://dummyimage.com/217x207.png/dddddd/000000",
    "groups": []
  },
  {
    "uuid": "239eb5f6-0f6c-494f-bab8-7718b1dd4382",
    "name": "Natalina",
    "isFavourite": true,
    "image": "http://dummyimage.com/170x228.png/ff4444/ffffff",
    "groups": []
  },
  {
    "uuid": "847fc5e4-53c3-4d9b-8535-b2ceac25460f",
    "name": "Hirsch",
    "isFavourite": false,
    "image": "http://dummyimage.com/158x107.bmp/dddddd/000000",
    "groups": []
  }
]